{"00":{"Country":"Ireland","Image":"2Jet","Int":"0","Op":"RYR","Owner":null,"Short":"B737-800","Trail":"0","Type":"Boeing 737NG 8AS/W","r":"EI-EBC","t":"B738"},"01":{"Country":"Ireland","Image":"2Jet","Int":"0","Op":"RYR","Owner":null,"Short":"B737-800","Trail":"0","Type":"Boeing 737NG 8AS/W","r":"EI-EBD","t":"B738"},"02":{"Country":"Ireland","Image":"2Jet","Int":"0","Op":"RYR","Owner":null,"Short":"B737-800","Trail":"0","Type":"Boeing 737NG 8AS/W","r":"EI-EBE","t":"B738"},"03":{"Country":"Ireland","Image":"2Jet","Int":"0","Op":"RYR","Owner":null,"Short":"B737-800","Trail":"0","Type":"Boeing 737NG 8AS/W","r":"EI-EBF","t":"B738"},"04":{"Country":"Ireland","Image":"2Jet","Int":"0","Op":"RYR","Owner":null,"Short":"B737-800","Trail":"0","Type":"Boeing 737NG 8AS/W","r":"EI-EBG","t":"B738"},"05":{"Country":"Ireland","Image":"2Jet","Int":"0","Op":"RYR","Owner":null,"Short":"B737-800","Trail":"0","Type":"Boeing 737NG 8AS/W","r":"EI-EBH","t":"B738"},"06":{"Country":"Ireland","Image":"2Jet","Int":"0","Op":"RYR","Owner":null,"Short":"B737-800","Trail":"0","Type":"Boeing 737NG 8AS/W","r":"EI-EBI","t":"B738"},"07":{"Country":"Ireland","Image":"2Jet","Int":"0","Op":"RYR","Owner":null,"Short":"B737-800","Trail":"0","Type":"Boeing 737NG 8AS/W","r":"EI-EBK","t":"B738"},"08":{"Country":"Ireland","Image":"2Jet","Int":"0","Op":"RYR","Owner":null,"Short":"B737-800","Trail":"0","Type":"Boeing 737NG 8AS/W","r":"EI-EBL","t":"B738"},"09":{"Country":"Ireland","Int":"0","Owner":null,"Trail":"0"},"0E":{"Country":"Ireland","Int":"0","Owner":null,"Trail":"0"},"0F":{"Country":"Ireland","Image":"2Jet","Int":"0","Op":"BPA","Owner":null,"Short":"B737-800","Trail":"0","Type":"Boeing 737NG 86N","r":"EI-FSJ","t":"B738"},"11":{"Country":"Ireland","Image":"Heli","Int":"0","Owner":null,"Short":"Robinson","Trail":"0","Type":"Robinson R44 Raven II","r":"EI-LAD","t":"R44"},"13":{"Country":"Ireland","Image":"2Jet","Int":"0","Owner":null,"Short":"B762-300","Trail":"0","Type":"Boeing 767-3Q8","r":"EI-ECB","t":"B763"},"18":{"Country":"Ireland","Image":"2Jet","Int":"0","Op":"ADH","Owner":null,"Short":"A320","Trail":"0","Type":"Airbus A320-216","r":"EI-DSV","t":"A320"},"19":{"Country":"Ireland","Image":"2Jet","Int":"0","Op":"AZA","Owner":null,"Short":"A320","Trail":"0","Type":"Airbus A320 216","r":"EI-DSW","t":"A320"},"1A":{"Country":"Ireland","Image":"Micro","Int":"0","Op":"IBK","Owner":null,"Short":"Hamsa ","Trail":"0","Type":"Boeing 737NG 8JP/W","r":"EI-FJV","t":"B738"},"1B":{"Int":"0","Owner":null,"Trail":"0"},"1C":{"Country":"Ireland","Int":"0","Owner":null,"Trail":"0"},"1D":{"Country":"Ireland","Int":"0","Owner":null,"Trail":"0"},"1E":{"Country":"Ireland","Int":"0","Owner":null,"Trail":"0"},"1F":{"Country":"Ireland","Int":"0","Owner":null,"Trail":"0"},"20":{"Country":"Ireland","Image":"BJet","Int":"0","Op":"HYR","Owner":null,"Short":"Dominie","Trail":"0","Type":"Hawker 800XP","r":"EI-ECE","t":"H25B"},"21":{"Country":"Ireland","Int":"0","Owner":null,"Trail":"0"},"25":{"Country":"Ireland","Image":"2Jet","Int":"0","Op":"BPA","Owner":null,"Short":"B737-800","Trail":"0","Type":"Boeing 737-86N","r":"EI-ECM","t":"B738"},"26":{"Country":"Ireland","Image":"2Jet","Int":"0","Op":"RYR","Owner":null,"Short":"B737-800","Trail":"0","Type":"Boeing 737NG 8AS/W","r":"EI-FRY","t":"B738"},"27":{"Country":"Ireland","Image":"2Jet","Int":"0","Op":"RYR","Owner":null,"Short":"B737-800","Trail":"0","Type":"Boeing 737NG 800/W","r":"EI-FRZ","t":"B738"},"2B":{"Country":"Ireland","Int":"0","Owner":null,"Trail":"0"},"2C":{"Country":"Ireland","Int":"0","Owner":null,"Trail":"0"},"2D":{"Country":"Ireland","Int":"0","Owner":null,"Trail":"0"},"2E":{"Country":"Ireland","Image":"BJet","Int":"0","Owner":null,"Short":"Citation","Trail":"0","Type":"Cessna Citation CJ2+","r":"EI-ECR","t":"C25A"},"30":{"Country":"Ireland","Image":"2Jet","Int":"0","Op":"ADH","Owner":null,"Short":"A320","Trail":"0","Type":"Airbus A320-216","r":"EI-DSX","t":"A320"},"31":{"Int":"0","Owner":null,"Trail":"0"},"32":{"Country":"Ireland","Image":"2Jet","Int":"0","Owner":null,"Short":"A319","Trail":"0","Type":"Airbus A319-132","r":"EI-ECX","t":"A319"},"33":{"Country":"Ireland","Image":"2Jet","Int":"0","Owner":null,"Short":"A319","Trail":"0","Type":"Airbus A319-132","r":"EI-ECY","t":"A319"},"35":{"Int":"0","Owner":null,"Trail":"0"},"36":{"Country":"Ireland","Image":"2Jet","Int":"0","Op":"RYR","Owner":null,"Short":"B737-800","Trail":"0","Type":"Boeing 737NG 8AS/W","r":"EI-EBM","t":"B738"},"37":{"Country":"Ireland","Image":"2Jet","Int":"0","Op":"RYR","Owner":null,"Short":"B737-800","Trail":"0","Type":"Boeing 737NG 8AS/W","r":"EI-EBN","t":"B738"},"38":{"Country":"Ireland","Image":"2Jet","Int":"0","Op":"RYR","Owner":null,"Short":"B737-800","Trail":"0","Type":"Boeing 737NG 8AS/W","r":"EI-EBO","t":"B738"},"39":{"Country":"Ireland","Image":"2Jet","Int":"0","Op":"RYR","Owner":null,"Short":"B737-800","Trail":"0","Type":"Boeing 737NG 8AS/W","r":"EI-EBP","t":"B738"},"3A":{"Country":"Ireland","Image":"2Jet","Int":"0","Op":"RYR","Owner":null,"Short":"B737-800","Trail":"0","Type":"Boeing 737NG 8AS/W","r":"EI-EBR","t":"B738"},"3B":{"Country":"Ireland","Image":"2Jet","Int":"0","Op":"RYR","Owner":null,"Short":"B737-800","Trail":"0","Type":"Boeing 737NG 8AS/W","r":"EI-EBS","t":"B738"},"3C":{"Country":"Ireland","Image":"2Jet","Int":"0","Op":"RYR","Owner":null,"Short":"B737-800","Trail":"0","Type":"Boeing 737-8AS","r":"EI-EBT","t":"B738"},"3D":{"Country":"Ireland","Image":"2Jet","Int":"0","Op":"RYR","Owner":null,"Short":"B737-800","Trail":"0","Type":"Boeing 737NG 8AS/W","r":"EI-EBV","t":"B738"},"3E":{"Country":"Ireland","Image":"2Jet","Int":"0","Op":"RYR","Owner":null,"Short":"B737-800","Trail":"0","Type":"Boeing 737NG 8AS/W","r":"EI-EBW","t":"B738"},"3F":{"Country":"Ireland","Image":"2Jet","Int":"0","Op":"RYR","Owner":null,"Short":"B737-800","Trail":"0","Type":"Boeing 737NG 8AS/W","r":"EI-EBX","t":"B738"},"40":{"Country":"Ireland","Image":"2Jet","Int":"0","Op":"RYR","Owner":null,"Short":"B737-800","Trail":"0","Type":"Boeing 737NG 8AS/W","r":"EI-EBY","t":"B738"},"41":{"Country":"Ireland","Image":"2Jet","Int":"0","Op":"RYR","Owner":null,"Short":"B737-800","Trail":"0","Type":"Boeing 737NG 8AS/W","r":"EI-EBZ","t":"B738"},"43":{"Country":"Ireland","Int":"0","Owner":null,"Trail":"0"},"45":{"Country":"Ireland","Image":"2Jet","Int":"0","Op":"RYR","Owner":null,"Short":"B737-800","Trail":"0","Type":"Boeing 737NG 800/W","r":"EI-FTH","t":"B738"},"47":{"Country":"Ireland","Int":"0","Owner":null,"Trail":"0"},"49":{"Country":"Ireland","Int":"0","Owner":null,"Trail":"0"},"4C":{"Country":"Ireland","Image":"2Jet","Int":"0","Owner":null,"Short":"B777-200","Trail":"0","Type":"Boeing 777 222ER","r":"EI-UNW","t":"B772"},"4E":{"Country":"Ireland","Image":"2Jet","Int":"0","Op":"EIN","Owner":null,"Short":"A300-300","Trail":"0","Type":"Airbus A330 302E","r":"EI-EAV","t":"A333"},"4F":{"Country":"Ireland","Int":"0","Owner":null,"Trail":"0"},"56":{"Country":"Ireland","Image":"2Jet","Int":"0","Op":"BCY","Owner":null,"Short":"Sukhoi","Trail":"0","Type":"Sukhoi Superjet 100 95 B","r":"EI-FWC","t":"SU95"},"57":{"Country":"Ireland","Image":"2Jet","Int":"0","Op":"AZA","Owner":null,"Short":"A320","Trail":"0","Type":"Airbus A320 216","r":"EI-DSY","t":"A320"},"58":{"Country":"Ireland","Image":"2Jet","Int":"0","Op":"ADH","Owner":null,"Short":"A320","Trail":"0","Type":"Airbus A320-216","r":"EI-DSZ","t":"A320"},"59":{"Country":"Ireland","Image":"2Jet","Int":"0","Op":"AZA","Owner":null,"Short":"A320","Trail":"0","Type":"Airbus A320 216","r":"EI-DTA","t":"A320"},"5A":{"Country":"Ireland","Image":"2Jet","Int":"0","Op":"JET","Owner":null,"Short":"A319","Trail":"0","Type":"Airbus A319-132","r":"EI-EDM","t":"A319"},"5B":{"Country":"Ireland","Int":"0","Owner":null,"Trail":"0"},"5C":{"Country":"Ireland","Image":"2Jet","Int":"0","Op":"RYR","Owner":null,"Short":"B737-800","Trail":"0","Type":"Boeing 737-8AS","r":"EI-EFA","t":"B738"},"5D":{"Country":"Ireland","Image":"2Jet","Int":"0","Owner":null,"Short":"B737-800","Trail":"0","Type":"Boeing 737NG 8AS/W","r":"EI-EFB","t":"B738"},"5E":{"Country":"Ireland","Image":"2Jet","Int":"0","Op":"RYR","Owner":null,"Short":"B737-800","Trail":"0","Type":"Boeing 737NG 8AS/W","r":"EI-EFC","t":"B738"},"5F":{"Country":"Ireland","Image":"2Jet","Int":"0","Op":"RYR","Owner":null,"Short":"B737-800","Trail":"0","Type":"Boeing 737NG 8AS/W","r":"EI-EFD","t":"B738"},"60":{"Country":"Ireland","Image":"2Jet","Int":"0","Op":"RYR","Owner":null,"Short":"B737-800","Trail":"0","Type":"Boeing 737NG 8AS/W","r":"EI-EFE","t":"B738"},"61":{"Country":"Ireland","Image":"2Jet","Int":"0","Op":"RYR","Owner":null,"Short":"B737-800","Trail":"0","Type":"Boeing 737NG 8AS/W","r":"EI-EFF","t":"B738"},"62":{"Country":"Ireland","Image":"2Jet","Int":"0","Op":"RYR","Owner":null,"Short":"B737-800","Trail":"0","Type":"Boeing 737NG 8AS/W","r":"EI-EFG","t":"B738"},"63":{"Country":"Ireland","Image":"2Jet","Int":"0","Op":"RYR","Owner":null,"Short":"B737-800","Trail":"0","Type":"Boeing 737NG 8AS/W","r":"EI-EFH","t":"B738"},"64":{"Country":"Ireland","Image":"2Jet","Int":"0","Op":"RYR","Owner":null,"Short":"B737-800","Trail":"0","Type":"Boeing 737NG 8AS/W","r":"EI-EFI","t":"B738"},"65":{"Country":"Ireland","Image":"2Jet","Int":"0","Op":"RYR","Owner":null,"Short":"B737-800","Trail":"0","Type":"Boeing 737NG 8AS/W","r":"EI-EFJ","t":"B738"},"66":{"Country":"Ireland","Image":"2Jet","Int":"0","Op":"RYR","Owner":null,"Short":"B737-800","Trail":"0","Type":"Boeing 737NG 8AS/W","r":"EI-EFK","t":"B738"},"67":{"Country":"Ireland","Image":"2Jet","Int":"0","Op":"RYR","Owner":null,"Short":"B737-800","Trail":"0","Type":"Boeing 737-8AS","r":"EI-EFL","t":"B738"},"68":{"Country":"Ireland","Image":"2Jet","Int":"0","Op":"RYR","Owner":null,"Short":"B737-800","Trail":"0","Type":"Boeing 737NG 8AS/W","r":"EI-EFM","t":"B738"},"69":{"Country":"Ireland","Image":"2Jet","Int":"0","Op":"RYR","Owner":null,"Short":"B737-800","Trail":"0","Type":"Boeing 737NG 8AS/W","r":"EI-EFN","t":"B738"},"6A":{"Country":"Ireland","Image":"2Jet","Int":"0","Op":"RYR","Owner":null,"Short":"B737-800","Trail":"0","Type":"Boeing 737NG 8AS/W","r":"EI-EFO","t":"B738"},"6B":{"Country":"Ireland","Int":"0","Owner":null,"Trail":"0"},"6C":{"Int":"0","Owner":null,"Trail":"0"},"6D":{"Country":"Ireland","Int":"0","Owner":null,"Trail":"0"},"6E":{"Country":"Ireland","Int":"0","Owner":null,"Trail":"0"},"6F":{"Country":"Ireland","Image":"2Jet","Int":"0","Op":"EIN","Owner":null,"Short":"A320","Trail":"0","Type":"Airbus A320 214","r":"EI-EDP","t":"A320"},"70":{"Country":"Ireland","Image":"2Jet","Int":"0","Op":"EIN","Owner":null,"Short":"A320","Trail":"0","Type":"Airbus A320 214","r":"EI-EDS","t":"A320"},"72":{"Country":"Ireland","Int":"0","Owner":null,"Trail":"0"},"74":{"Country":"Ireland","Int":"0","Owner":null,"Trail":"0"},"78":{"Country":"Ireland","Image":"Light","Int":"0","Owner":null,"Short":"Vans","Trail":"0","Type":"Vans RV-7","r":"EI-VII","t":"RV7"},"7A":{"Country":"Ireland","Int":"0","Owner":null,"Trail":"0"},"7B":{"Country":"Ireland","Int":"0","Owner":null,"Trail":"0"},"7D":{"Country":"Ireland","Image":"2Jet","Int":"0","Op":"TSO","Owner":null,"Short":"B737-800","Trail":"0","Type":"Boeing 737-8K5","r":"EI-EDZ","t":"B738"},"7E":{"Country":"Ireland","Image":"2Jet","Int":"0","Op":"TSO","Owner":null,"Short":"B737-800","Trail":"0","Type":"Boeing 737-8K5","r":"EI-EEA","t":"B738"},"7F":{"Country":"Ireland","Int":"0","Owner":null,"Trail":"0"},"80":{"Country":"Ireland","Image":"2Jet","Int":"0","Op":"BPA","Owner":null,"Short":"B762-300","Trail":"0","Type":"Boeing 767-31AER","r":"EI-EED","t":"B763"},"82":{"Country":"Ireland","Image":"2Jet","Int":"0","Op":"EIN","Owner":null,"Short":"A300-300","Trail":"0","Type":"Airbus A330 302E","r":"EI-EDY","t":"A333"},"83":{"Country":"Ireland","Image":"2Jet","Int":"0","Op":"AZA","Owner":null,"Short":"A320","Trail":"0","Type":"Airbus A320 216","r":"EI-DTB","t":"A320"},"84":{"Country":"Ireland","Image":"BJet","Int":"0","Owner":null,"Short":"GulfStream","Trail":"0","Type":"Gulfstream Aerospace G650","r":"EI-LSN","t":"GLF6"},"85":{"Country":"Ireland","Image":"BJet","Int":"0","Owner":null,"Short":"GulfStream","Trail":"0","Type":"Gulfstream Aerospace G550","r":"EI-LSY","t":"GLF5"},"87":{"Country":"Ireland","Image":"BJet","Int":"0","Op":"HYR","Owner":null,"Short":"Dominie","Trail":"0","Type":"Hawker 900XP","r":"EI-JJJ","t":"H25B"},"88":{"Country":"Ireland","Image":"2Jet","Int":"0","Op":"EIN","Owner":null,"Short":"A320","Trail":"0","Type":"Airbus A320 214","r":"EI-DVJ","t":"A320"},"8B":{"Country":"Ireland","Int":"0","Owner":null,"Trail":"0"},"8C":{"Country":"Ireland","Image":"2Jet","Int":"0","Op":"AZA","Owner":null,"Short":"A320","Trail":"0","Type":"Airbus A320-216","r":"EI-DTC","t":"A320"},"8D":{"Country":"Ireland","Image":"2Jet","Int":"0","Owner":null,"Short":"B737-800","Trail":"0","Type":"737-8AS (W)","r":"EI-FTS","t":"B738"},"8E":{"Country":"Ireland","Image":"2Jet","Int":"0","Owner":null,"Short":"B737-800","Trail":"0","Type":"737-8AS (W)","r":"EI-FTT","t":"B738"},"8F":{"Country":"Ireland","Image":"2Jet","Int":"0","Owner":null,"Short":"B737-800","Trail":"0","Type":"Boeing 737-8AS (W)","r":"EI-FTV","t":"B738"},"90":{"Country":"Ireland","Image":"2Jet","Int":"0","Op":"AZA","Owner":null,"Short":"A320","Trail":"0","Type":"Airbus A320 216","r":"EI-DTD","t":"A320"},"93":{"Country":"Ireland","Int":"0","Owner":null,"Trail":"0"},"94":{"Country":"Ireland","Int":"0","Owner":null,"Trail":"0"},"95":{"Country":"Ireland","Image":"Glider","Int":"0","Owner":null,"Short":"Flugzeugbau","Trail":"0","Type":"DG Flugzeugbau DG-808xB Competition","r":"EI-GMN","t":"DG80"},"96":{"Country":"Ireland","Int":"0","Owner":null,"Trail":"0"},"98":{"Country":"Ireland","Image":"2Jet","Int":"0","Op":"AZA","Owner":null,"Short":"A320","Trail":"0","Type":"Airbus A320 216","r":"EI-DTE","t":"A320"},"99":{"Int":"0","Owner":null,"Trail":"0"},"9A":{"Country":"Ireland","Image":"2Jet","Int":"0","Op":"RYR","Owner":null,"Short":"B737-800","Trail":"0","Type":"Boeing 737NG 8AS/W","r":"EI-FTB","t":"B738"},"9B":{"Country":"Ireland","Image":"2Jet","Int":"0","Op":"RYR","Owner":null,"Short":"B737-800","Trail":"0","Type":"Boeing 737NG 8AS/W","r":"EI-FTC","t":"B738"},"9C":{"Country":"Ireland","Image":"2Jet","Int":"0","Op":"RYR","Owner":null,"Short":"B737-800","Trail":"0","Type":"Boeing 737NG 800/W","r":"EI-FTD","t":"B738"},"9D":{"Country":"Ireland","Image":"2Jet","Int":"0","Op":"RYR","Owner":null,"Short":"B737-800","Trail":"0","Type":"Boeing 737NG 8AS/W","r":"EI-FTE","t":"B738"},"A2":{"Country":"Ireland","Image":"BJet","Int":"0","Owner":null,"Short":"EMB-145","Trail":"0","Type":"Embraer EMB145","r":"EI-EEJ","t":"E145"},"A3":{"Country":"Ireland","Int":"0","Owner":null,"Trail":"0"},"A5":{"Country":"Ireland","Int":"0","Owner":null,"Trail":"0"},"A6":{"Country":"Ireland","Int":"0","Owner":null,"Trail":"0"},"A7":{"Country":"Ireland","Image":"2Jet","Int":"0","Op":"RYR","Owner":null,"Short":"B737-800","Trail":"0","Type":"Boeing 737NG 8AS/W","r":"EI-EFP","t":"B738"},"A8":{"Country":"Ireland","Image":"2Jet","Int":"0","Op":"RYR","Owner":null,"Short":"B737-800","Trail":"0","Type":"Boeing 737NG 8AS/W","r":"EI-EFR","t":"B738"},"A9":{"Country":"Ireland","Image":"2Jet","Int":"0","Op":"RYR","Owner":null,"Short":"B737-800","Trail":"0","Type":"Boeing 737NG 8AS/W","r":"EI-EFS","t":"B738"},"AA":{"Country":"Ireland","Image":"2Jet","Int":"0","Op":"RYR","Owner":null,"Short":"B737-800","Trail":"0","Type":"Boeing 737NG 8AS/W","r":"EI-EFT","t":"B738"},"AB":{"Country":"Ireland","Image":"2Jet","Int":"0","Op":"RYR","Owner":null,"Short":"B737-800","Trail":"0","Type":"Boeing 737NG 8AS/W","r":"EI-EFV","t":"B738"},"AC":{"Country":"Ireland","Image":"2Jet","Int":"0","Op":"RYR","Owner":null,"Short":"B737-800","Trail":"0","Type":"Boeing 737NG 8AS/W","r":"EI-EFW","t":"B738"},"AD":{"Country":"Ireland","Int":"0","Owner":null,"Trail":"0"},"AF":{"Country":"Ireland","Image":"Missing","Int":"0","Owner":null,"Trail":"0"},"B0":{"Country":"Ireland","Image":"2Jet","Int":"0","Owner":null,"Short":"B737-800","Trail":"0","Type":"737-8AS (W)","r":"EI-FTW","t":"B738"},"B1":{"Country":"Ireland","Image":"Light","Int":"0","Owner":null,"Short":"Vans","Trail":"0","Type":"Vans RV-7","r":"EI-EEO","t":"RV7"},"B3":{"Country":"Ireland","Image":"2Jet","Int":"0","Op":"RYR","Owner":null,"Short":"B737-800","Trail":"0","Type":"Boeing 737NG 8AS/W","r":"EI-EFX","t":"B738"},"B4":{"Country":"Ireland","Image":"2Jet","Int":"0","Op":"RYR","Owner":null,"Short":"B737-800","Trail":"0","Type":"Boeing 737NG 8AS/W","r":"EI-EFY","t":"B738"},"B5":{"Country":"Ireland","Image":"2Jet","Int":"0","Op":"RYR","Owner":null,"Short":"B737-800","Trail":"0","Type":"Boeing 737NG 8AS/W","r":"EI-EFZ","t":"B738"},"B6":{"Country":"Ireland","Image":"2Jet","Int":"0","Op":"RYR","Owner":null,"Short":"B737-800","Trail":"0","Type":"Boeing 737NG 8AS/W","r":"EI-EGA","t":"B738"},"B7":{"Country":"Ireland","Image":"2Jet","Int":"0","Op":"RYR","Owner":null,"Short":"B737-800","Trail":"0","Type":"Boeing 737NG 8AS/W","r":"EI-EGB","t":"B738"},"B8":{"Country":"Ireland","Int":"0","Owner":null,"Trail":"0"},"B9":{"Country":"Ireland","Image":"2Jet","Int":"0","Op":"RYR","Owner":null,"Short":"B737-800","Trail":"0","Type":"Boeing 737NG 8AS/W","r":"EI-EGC","t":"B738"},"BB":{"Country":"Ireland","Int":"0","Owner":null,"Trail":"0"},"BC":{"Country":"Ireland","Int":"0","Owner":null,"Trail":"0"},"BD":{"Country":"Ireland","Image":"2Jet","Int":"0","Op":"AZA","Owner":null,"Short":"A320","Trail":"0","Type":"Airbus A320 216","r":"EI-DTF","t":"A320"},"BE":{"Country":"Ireland","Image":"2Jet","Int":"0","Owner":null,"Short":"B737-800","Trail":"0","Type":"737-8AS (W)","r":"EI-FTY","t":"B738"},"BF":{"Country":"Ireland","Image":"2Jet","Int":"0","Op":"AZA","Owner":null,"Short":"A320","Trail":"0","Type":"Airbus A320 216","r":"EI-DTG","t":"A320"},"C0":{"Country":"Ireland","Image":"BJet","Int":"0","Owner":null,"Short":"Citation","Trail":"0","Type":"Cessna 510 Citation Mustang","r":"EI-SFD","t":"C510"},"C1":{"Country":"Ireland","Image":"BJet","Int":"0","Owner":null,"Short":"Citation","Trail":"0","Type":"Cessna 510 Citation Mustang","r":"EI-SFE","t":"C510"},"C2":{"Country":"Ireland","Image":"2Jet","Int":"0","Op":"RYR","Owner":null,"Short":"B737-800","Trail":"0","Type":"Boeing 737NG 800/W","r":"EI-FTZ","t":"B738"},"C4":{"Country":"Ireland","Image":"2Jet","Int":"0","Op":"RYR","Owner":null,"Short":"B737-800","Trail":"0","Type":"Boeing 737NG 800/W","r":"EI-FZA","t":"B738"},"C6":{"Country":"Ireland","Int":"0","Owner":null,"Trail":"0"},"C8":{"Country":"Ireland","Image":"2Jet","Int":"0","Owner":null,"Short":"B737-300","Trail":"0","Type":"Boeing 737-375","r":"EI-EEW","t":"B733"},"CE":{"Country":"Ireland","Image":"2Jet","Int":"0","Owner":null,"Short":"A320","Trail":"0","Type":"Airbus A320-231","r":"EI-EEX","t":"A320"},"CF":{"Country":"Ireland","Image":"2Jet","Int":"0","Owner":null,"Short":"A320","Trail":"0","Type":"Airbus A320-231","r":"EI-EEY","t":"A320"},"D0":{"Country":"Ireland","Int":"0","Owner":null,"Trail":"0"},"D1":{"Int":"0","Owner":null,"Trail":"0"},"D2":{"Country":"Ireland","Image":"2Prop","Int":"0","Op":"ABR","Owner":null,"Short":"ATR","Trail":"0","Type":"Avions de Transport Regional ATR 72 201F","r":"EI-SLJ","t":"AT72"},"D4":{"Country":"Ireland","Int":"0","Owner":null,"Trail":"0"},"D6":{"Country":"Ireland","Image":"2Prop","Int":"0","Op":"STK","Owner":null,"Short":"ATR","Trail":"0","Type":"Avions de Transport Regional ATR 42 310","r":"EI-EHH","t":"AT43"},"D7":{"Country":"Ireland","Image":"2Jet","Int":"0","Op":"AZA","Owner":null,"Short":"A320","Trail":"0","Type":"Airbus A320 216","r":"EI-DTH","t":"A320"},"D9":{"Country":"Ireland","Int":"0","Owner":null,"Trail":"0"},"DA":{"Country":"Ireland","Int":"0","Owner":null,"Trail":"0"},"DD":{"Country":"Ireland","Image":"2Jet","Int":"0","Op":"AZA","Owner":null,"Short":"A320","Trail":"0","Type":"Airbus A320 216","r":"EI-DTI","t":"A320"},"DE":{"Country":"Ireland","Image":"2Jet","Int":"0","Op":"HYR","Owner":null,"Short":"Regional ","Trail":"0","Type":"Bombardier Challenger 850","r":"EI-EEZ","t":"CRJ2"},"E0":{"Country":"Ireland","Int":"0","Owner":null,"Trail":"0"},"E1":{"Country":"Ireland","Image":"2Jet","Int":"0","Op":"AZA","Owner":null,"Short":"A320","Trail":"0","Type":"Airbus A320 216","r":"EI-DTJ","t":"A320"},"E5":{"Country":"Ireland","Image":"2Jet","Int":"0","Op":"IBK","Owner":null,"Short":"B737-800","Trail":"0","Type":"Boeing 737NG 8JP/W","r":"EI-FVH","t":"B738"},"E6":{"Country":"Ireland","Image":"2Jet","Int":"0","Op":"IBK","Owner":null,"Short":"B737-800","Trail":"0","Type":"Boeing 737NG 800/W","r":"EI-FVI","t":"B738"},"E7":{"Country":"Ireland","Image":"2Jet","Int":"0","Owner":null,"Short":"B737-800","Trail":"0","Type":"737-8JP (W)","r":"EI-FVJ","t":"B738"},"E8":{"Country":"Ireland","Image":"2Jet","Int":"0","Op":"IBK","Owner":null,"Short":"B737-800","Trail":"0","Type":"Boeing 737NG 800/W","r":"EI-FVK","t":"B738"},"E9":{"Country":"Ireland","Image":"2Jet","Int":"0","Op":"IBK","Owner":null,"Short":"B737-800","Trail":"0","Type":"Boeing 737NG 800/W","r":"EI-FVL","t":"B738"},"EA":{"Country":"Ireland","Int":"0","Owner":null,"Trail":"0"},"EE":{"Country":"Ireland","Image":"Light","Int":"0","Owner":null,"Short":"Roko","Trail":"0","Type":"Roko Aero NG-4 HD","r":"EI-MIR","t":"NG4"},"EF":{"Country":"Ireland","Int":"0","Owner":null,"Trail":"0"},"F2":{"Country":"Ireland","Image":"2Jet","Int":"0","Owner":null,"Short":"B737-800","Trail":"0","Type":"737-86N (W)","r":"EI-GBB","t":"B738"},"F3":{"Country":"Ireland","Int":"0","Owner":null,"Trail":"0"},"F4":{"Country":"Ireland","Image":"BJet","Int":"0","Owner":null,"Short":"Falcon","Trail":"0","Type":"Dassault Falcon 2000EX","r":"EI-TDV","t":"F2TH"},"F5":{"Country":"Ireland","Image":"2Prop","Int":"0","Op":"ABR","Owner":null,"Short":"ATR","Trail":"0","Type":"Avions de Transport Regional ATR 72 212F","r":"EI-SLK","t":"AT72"},"F6":{"Country":"Ireland","Image":"2Jet","Int":"0","Op":"EEZ","Owner":null,"Short":"A330-200","Trail":"0","Type":"Airbus A330-223","r":"EI-EZL","t":"A332"},"F7":{"Country":"Ireland","Int":"0","Owner":null,"Trail":"0"},"F8":{"Country":"Ireland","Image":"Light","Int":"0","Owner":null,"Short":"SportsCuiser","Trail":"0","Type":"CZAW Sportcruiser","r":"EI-EHV","t":"CRUZ"},"F9":{"Country":"Ireland","Int":"0","Owner":null,"Trail":"0"},"FB":{"Country":"Ireland","Int":"0","Owner":null,"Trail":"0"},"FC":{"Country":"Ireland","Int":"0","Owner":null,"Trail":"0"},"FE":{"Country":"Ireland","Image":"2Jet","Int":"0","Op":"RYR","Owner":null,"Short":"B737-800","Trail":"0","Type":"Boeing 737NG 8AS/W","r":"EI-EKA","t":"B738"},"FF":{"Country":"Ireland","Image":"2Jet","Int":"0","Op":"RYR","Owner":null,"Short":"B737-800","Trail":"0","Type":"Boeing 737NG 8AS/W","r":"EI-EKB","t":"B738"}}