{"0000":{"Country":"Armenia","Int":"0","Owner":null,"Trail":"0"},"0007":{"Country":"Armenia","Image":"2Jet","Int":"0","Op":"RNV","Owner":null,"Short":"A319","Trail":"0","Type":"Airbus A319-132","r":"EK-32011","t":"A319"},"000C":{"Country":"Armenia","Image":"2Jet","Int":"0","Op":"LUR","Owner":null,"Short":"A320","Trail":"0","Type":"Airbus A320 211","r":"EK32008","t":"A320"},"0013":{"Country":"Armenia","Image":"4Prop","Int":"0","Op":"RNV","Owner":null,"Short":"Antonov","Trail":"0","Type":"Antonov AN12TBK","r":"EK-11001","t":"AN12"},"002F":{"Country":"Armenia","Image":"4Prop","Int":"0","Op":"ARR","Owner":null,"Short":"Antonov","Trail":"0","Type":"Antonov AN12","r":"EK-12104","t":"AN12"},"003C":{"Country":"Armenia","Image":"2Jet","Int":"0","Op":"RNV","Owner":null,"Short":"A319","Trail":"0","Type":"Airbus A319-132","r":"EK-RA01","t":"A319"},"004A":{"Country":"Armenia","Image":"2Jet","Int":"0","Op":"RNV","Owner":null,"Short":"A319","Trail":"0","Type":"Airbus A319-111","r":"EK-32007","t":"A319"},"0059":{"Country":"Armenia","Image":"2Jet","Int":"0","Op":"RNV","Owner":null,"Short":"Sukhoi","Trail":"0","Type":"Sukhoi 100-95LR","r":"EK-95015","t":"SU95"},"005A":{"Country":"Armenia","Image":"2Jet","Int":"0","Op":"RNV","Owner":null,"Short":"Sukhoi","Trail":"0","Type":"Sukhoi 100-95B  SuperJet","r":"EK-95016","t":"SU95"},"0076":{"Country":"Armenia","Image":"4Jet","Int":"0","Op":"VTF","Owner":null,"Short":"B747-200","Trail":"0","Type":"Boeing 747-281F","r":"EK-74723","t":"B742"},"0079":{"Country":"Armenia","Image":"4Jet","Int":"0","Op":"VTF","Owner":null,"Short":"B747-200","Trail":"0","Type":"Boeing 747-281F","r":"EK-74798","t":"B742"},"0087":{"Country":"Armenia","Image":"4Jet","Int":"0","Op":"VTF","Owner":null,"Short":"B747-200","Trail":"0","Type":"Boeing 747-281F","r":"EK-74799","t":"B742"},"009D":{"Country":"Armenia","Image":"2Jet","Int":"0","Op":"RNV","Owner":null,"Short":"B737-500","Trail":"0","Type":"Boeing 737-55S","r":"EK-73775","t":"B735"},"009F":{"Country":"Armenia","Image":"2Jet","Int":"0","Op":"RNV","Owner":null,"Short":"B737-500","Trail":"0","Type":"Boeing 737-55S","r":"EK-73772","t":"B735"},"00A2":{"Country":"Armenia","Int":"0","Owner":null,"Trail":"0"},"00A3":{"Country":"Armenia","Int":"0","Owner":null,"Trail":"0"},"0113":{"Country":"Armenia","Int":"0","Owner":null,"Trail":"0"},"02D9":{"Country":"Armenia","Int":"0","Owner":null,"Trail":"0"},"0408":{"Country":"Unknown or unassigned co","Int":"0","Owner":null,"Trail":"0"},"0432":{"Country":"Unknown or unassigned co","Int":"0","Owner":null,"Trail":"0"},"0492":{"Country":"Unknown or unassigned co","Int":"0","Owner":null,"Trail":"0"},"0493":{"Country":"Unknown or unassigned co","Int":"0","Owner":null,"Trail":"0"},"04C6":{"Country":"Unknown or unassigned co","Int":"0","Owner":null,"Trail":"0"},"04DF":{"Country":"Unknown or unassigned co","Int":"0","Owner":null,"Trail":"0"},"0513":{"Country":"Unknown or unassigned co","Int":"0","Owner":null,"Trail":"0"},"057F":{"Country":"Unknown or unassigned co","Int":"0","Owner":null,"Trail":"0"},"0580":{"Country":"Unknown or unassigned co","Int":"0","Owner":null,"Trail":"0"},"05A5":{"Country":"Unknown or unassigned co","Int":"0","Owner":null,"Trail":"0"},"05A6":{"Country":"Unknown or unassigned co","Int":"0","Owner":null,"Trail":"0"},"05BD":{"Country":"Unknown or unassigned co","Int":"0","Owner":null,"Trail":"0"},"05E3":{"Country":"Unknown or unassigned co","Int":"0","Owner":null,"Trail":"0"},"067F":{"Country":"Unknown or unassigned co","Int":"0","Owner":null,"Trail":"0"},"0683":{"Country":"Unknown or unassigned co","Int":"0","Owner":null,"Trail":"0"},"0684":{"Country":"Unknown or unassigned co","Int":"0","Owner":null,"Trail":"0"},"068F":{"Country":"Unknown or unassigned co","Int":"0","Owner":null,"Trail":"0"},"0691":{"Country":"Unknown or unassigned co","Int":"0","Owner":null,"Trail":"0"},"06AA":{"Country":"Unknown or unassigned co","Int":"0","Owner":null,"Trail":"0"},"06AB":{"Country":"Unknown or unassigned co","Int":"0","Owner":null,"Trail":"0"},"06C2":{"Country":"Unknown or unassigned co","Int":"0","Owner":null,"Trail":"0"},"06C4":{"Country":"Unknown or unassigned co","Int":"0","Owner":null,"Trail":"0"},"0718":{"Country":"Unknown or unassigned co","Int":"0","Owner":null,"Trail":"0"},"0757":{"Country":"Unknown or unassigned co","Int":"0","Owner":null,"Trail":"0"},"076C":{"Country":"Unknown or unassigned co","Int":"0","Owner":null,"Trail":"0"},"0771":{"Country":"Unknown or unassigned co","Int":"0","Owner":null,"Trail":"0"},"0774":{"Country":"Unknown or unassigned co","Int":"0","Owner":null,"Trail":"0"},"0788":{"Country":"Unknown or unassigned co","Int":"0","Owner":null,"Trail":"0"},"07B3":{"Country":"Unknown or unassigned co","Int":"0","Owner":null,"Trail":"0"},"07F0":{"Country":"Unknown or unassigned co","Int":"0","Owner":null,"Trail":"0"},"0801":{"Country":"Azerbaijan","Image":"2Jet","Int":"1","Op":"AHY","Owner":null,"Short":"A319","Trail":"5","Type":"Airbus ACJ319 115X","r":"4K-8888","t":"A319"},"0803":{"Country":"Azerbaijan","Image":"2Jet","Int":"0","Op":"AHY","Owner":null,"Short":"A319","Trail":"0","Type":"Airbus A319-111","r":"4K-AZ03","t":"A319"},"0804":{"Country":"Azerbaijan","Image":"2Jet","Int":"0","Op":"AHY","Owner":null,"Short":"A319","Trail":"0","Type":"Airbus A319-111","r":"4K-AZ04","t":"A319"},"0805":{"Country":"Azerbaijan","Image":"2Jet","Int":"0","Op":"AHY","Owner":null,"Short":"A319","Trail":"0","Type":"Airbus A319-111","r":"4K-AZ05","t":"A319"},"0806":{"Country":"Azerbaijan","Image":"BJet","Int":"0","Owner":null,"Short":"GulfStream","Trail":"0","Type":"Gulfstream Aerospace G550","r":"4K-AI06","t":"GLF5"},"0807":{"Country":"Azerbaijan","Image":"2Jet","Int":"1","Op":"AHY","Owner":null,"Short":"A320","Trail":"5","Type":"Airbus ACJ320 214X","r":"4K-AI07","t":"A320"},"0808":{"Country":"Azerbaijan","Image":"BJet","Int":"0","Owner":null,"Short":"GulfStream","Trail":"0","Type":"Gulfstream Aerospace G550","r":"4K-MEK8","t":"GLF5"},"080C":{"Country":"Azerbaijan","Int":"0","Owner":null,"Trail":"0"},"0826":{"Country":"Azerbaijan","Image":"2Jet","Int":"0","Op":"AHY","Owner":null,"Short":"B757-200","Trail":"0","Type":"Boeing 757-256","r":"4K-AZ38","t":"B752"},"082B":{"Country":"Azerbaijan","Image":"2Jet","Int":"0","Op":"AHY","Owner":null,"Short":"B757-200","Trail":"0","Type":"Boeing 757-2M6","r":"4K-AZ43","t":"B752"},"0836":{"Country":"Azerbaijan","Image":"2Jet","Int":"0","Op":"AHY","Owner":null,"Short":"A320","Trail":"0","Type":"Airbus A320-211","r":"4K-AZ54","t":"A320"},"0838":{"Country":"Azerbaijan","Image":"4Prop","Int":"0","Op":"AZQ","Owner":null,"Short":"Antonov","Trail":"0","Type":"Antonov AN12BP","r":"4K-AZ56","t":"AN12"},"083C":{"Country":"Azerbaijan","Image":"4Jet","Int":"0","Op":"AZQ","Owner":null,"Short":"Ilyushin","Trail":"0","Type":"Ilyushin IL-76 TD","r":"4K-AZ60","t":"IL76"},"084D":{"Country":"Azerbaijan","Image":"2Jet","Int":"0","Op":"AHY","Owner":null,"Short":"A320","Trail":"0","Type":"Airbus A320-214","r":"4K-AZ77","t":"A320"},"084E":{"Country":"Azerbaijan","Image":"2Jet","Int":"0","Op":"AHY","Owner":null,"Short":"A320","Trail":"0","Type":"Airbus A320-214","r":"4K-AZ78","t":"A320"},"084F":{"Country":"Azerbaijan","Image":"2Jet","Int":"0","Op":"AHY","Owner":null,"Short":"A320","Trail":"0","Type":"Airbus A320-214","r":"4K-AZ79","t":"A320"},"0850":{"Country":"Azerbaijan","Image":"2Jet","Int":"0","Op":"AHY","Owner":null,"Short":"A320","Trail":"0","Type":"Airbus A320-214","r":"4K-AZ80","t":"A320"},"0851":{"Country":"Azerbaijan","Image":"2Jet","Int":"0","Op":"AHY","Owner":null,"Short":"B762-300","Trail":"0","Type":"Boeing 767 32LER","r":"4K-AZ81","t":"B763"},"0852":{"Country":"Azerbaijan","Image":"2Jet","Int":"0","Op":"AHY","Owner":null,"Short":"B762-300","Trail":"0","Type":"Boeing 767 32LER/W","r":"4K-AZ82","t":"B763"},"0853":{"Country":"Azerbaijan","Image":"2Jet","Int":"0","Op":"AHY","Owner":null,"Short":"A320","Trail":"0","Type":"Airbus A320-214","r":"4K-AZ83","t":"A320"},"0854":{"Country":"Azerbaijan","Image":"2Jet","Int":"0","Op":"AHY","Owner":null,"Short":"A320","Trail":"0","Type":"Airbus A320 214","r":"4K-AZ84","t":"A320"},"0855":{"Country":"Azerbaijan","Image":"4Jet","Int":"0","Op":"AHY","Owner":null,"Short":"A340-500","Trail":"0","Type":"Airbus A340 542","r":"4K-AZ85","t":"A345"},"0856":{"Country":"Azerbaijan","Image":"4Jet","Int":"0","Op":"AHY","Owner":null,"Short":"A340-500","Trail":"0","Type":"Airbus A340 542","r":"4K-AZ86","t":"A345"},"0858":{"Country":"Azerbaijan","Image":"BJet","Int":"0","Owner":null,"Short":"GulfStream","Trail":"0","Type":"Gulfstream Aerospace G200","r":"4K-AZ88","t":"G200"},"085B":{"Country":"Azerbaijan","Int":"0","Owner":null,"Trail":"0"},"0864":{"Country":"Azerbaijan","Int":"0","Owner":null,"Trail":"0"},"0865":{"Country":"Azerbaijan","Image":"4Jet","Int":"0","Op":"AZQ","Owner":null,"Short":"Ilyushin","Trail":"0","Type":"Ilyushin IL-76 TD-90SW","r":"4K-AZ101","t":"IL76"},"0896":{"Country":"Azerbaijan","Int":"0","Owner":null,"Trail":"0"},"08CB":{"Country":"Azerbaijan","Int":"0","Owner":null,"Trail":"0"},"08D0":{"Country":"Azerbaijan","Image":"BJet","Int":"0","Op":"ESW","Owner":null,"Short":"GulfStream","Trail":"0","Type":"IAI Ltd Gulfstream G280","r":"4K-AZ208","t":"G280"},"08D1":{"Country":"Azerbaijan","Int":"0","Owner":null,"Trail":"0"},"08F6":{"Country":"Azerbaijan","Int":"0","Owner":null,"Trail":"0"},"08F8":{"Country":"Azerbaijan","Int":"0","Owner":null,"Trail":"0"},"090D":{"Country":"Azerbaijan","Int":"0","Owner":null,"Trail":"0"},"090E":{"Country":"Azerbaijan","Int":"0","Owner":null,"Trail":"0"},"0918":{"Country":"Azerbaijan","Image":"BJet","Int":"0","Op":"ESW","Owner":null,"Short":"GulfStream","Trail":"0","Type":"Gulfstream 280","r":"4K-AZ280","t":"G280"},"0947":{"Country":"Azerbaijan","Int":"0","Owner":null,"Trail":"0"},"0955":{"Country":"Azerbaijan","Int":"0","Owner":null,"Trail":"0"},"09AB":{"Country":"Azerbaijan","Int":"0","Owner":null,"Trail":"0"},"09B9":{"Country":"Azerbaijan","Int":"0","Owner":null,"Trail":"0"},"09D0":{"Country":"Azerbaijan","Int":"0","Owner":null,"Trail":"0"},"09DF":{"Country":"Azerbaijan","Int":"0","Owner":null,"Trail":"0"},"0A2A":{"Country":"Azerbaijan","Int":"0","Owner":null,"Trail":"0"},"0A33":{"Country":"Azerbaijan","Int":"0","Owner":null,"Trail":"0"},"0A34":{"Country":"Azerbaijan","Int":"0","Owner":null,"Trail":"0"},"0A43":{"Country":"Azerbaijan","Int":"0","Owner":null,"Trail":"0"},"0A5B":{"Country":"Azerbaijan","Int":"0","Owner":null,"Trail":"0"},"0A70":{"Country":"Azerbaijan","Int":"0","Owner":null,"Trail":"0"},"0AFD":{"Country":"Azerbaijan","Int":"0","Owner":null,"Trail":"0"},"0B04":{"Country":"Azerbaijan","Int":"0","Owner":null,"Trail":"0"},"0B18":{"Country":"Azerbaijan","Int":"0","Owner":null,"Trail":"0"},"0B20":{"Country":"Azerbaijan","Image":"4Jet","Int":"0","Op":"AZQ","Owner":null,"Short":"B747-400","Trail":"0","Type":"Boeing 747-4R7F (SCD)","r":"4K-800","t":"B744"},"0B21":{"Country":"Azerbaijan","Image":"4Jet","Int":"0","Op":"AZG","Owner":null,"Short":"B747-400","Trail":"0","Type":"Boeing 747 4R7F","r":"4K-SW888","t":"B744"},"0B26":{"Country":"Azerbaijan","Int":"0","Owner":null,"Trail":"0"},"0B27":{"Country":"Azerbaijan","Int":"0","Owner":null,"Trail":"0"},"0B33":{"Country":"Azerbaijan","Int":"0","Owner":null,"Trail":"0"},"0B44":{"Country":"Azerbaijan","Int":"0","Owner":null,"Trail":"0"},"0B46":{"Country":"Azerbaijan","Int":"0","Owner":null,"Trail":"0"},"0B70":{"Country":"Azerbaijan","Image":"2Jet","Int":"0","Op":"AZQ","Owner":null,"Short":"B762-300","Trail":"0","Type":"Boeing 767-32LF","r":"4K-SW880","t":"B763"},"0B78":{"Country":"Azerbaijan","Image":"BJet","Int":"0","Owner":null,"Short":"GulfStream","Trail":"0","Type":"Gulfstream Aerospace G450","r":"4K-AZ888","t":"GLF4"},"0BB7":{"Country":"Azerbaijan","Int":"0","Owner":null,"Trail":"0"},"0BB9":{"Country":"Azerbaijan","Image":"2Jet","Int":"0","Op":"AZQ","Owner":null,"Short":"B762-300","Trail":"0","Type":"Boeing 767-32LF","r":"4K-SW808","t":"B763"},"0BBE":{"Country":"Azerbaijan","Image":"4Jet","Int":"0","Op":"AZG","Owner":null,"Short":"B747-400","Trail":"0","Type":"Boeing 747 4R7F","r":"4K-SW008","t":"B744"},"0BBF":{"Country":"Azerbaijan","Image":"2Jet","Int":"0","Op":"AHY","Owner":null,"Short":"B757-200","Trail":"0","Type":"Boeing 757 22L","r":"4K-AZ11","t":"B752"},"0BC0":{"Country":"Azerbaijan","Image":"4Jet","Int":"1","Op":"AHY","Owner":null,"Short":"A340-600","Trail":"5","Type":"Airbus A340ACJ 642X","r":"4K-AI08","t":"A346"},"0BC4":{"Country":"Azerbaijan","Image":"BJet","Int":"1","Op":"AHY","Owner":null,"Short":"GulfStream","Trail":"5","Type":"Gulfstream Aerospace G650","r":"4K-AI88","t":"GLF6"},"0BE6":{"Country":"Azerbaijan","Int":"0","Owner":null,"Trail":"0"},"0BE8":{"Country":"Azerbaijan","Image":"2Jet","Int":"0","Op":"AHY","Owner":null,"Short":"B762-300","Trail":"0","Type":"Boeing 767 32LER","r":"4K-AI01","t":"B763"},"0C4D":{"Country":"Unknown or unassigned co","Int":"0","Owner":null,"Trail":"0"},"0C50":{"Country":"Unknown or unassigned co","Int":"0","Owner":null,"Trail":"0"},"0C70":{"Country":"Unknown or unassigned co","Int":"0","Owner":null,"Trail":"0"},"0C75":{"Country":"Unknown or unassigned co","Int":"0","Owner":null,"Trail":"0"},"0CCF":{"Country":"Unknown or unassigned co","Int":"0","Owner":null,"Trail":"0"},"0CD1":{"Country":"Unknown or unassigned co","Int":"0","Owner":null,"Trail":"0"},"0CF9":{"Country":"Unknown or unassigned co","Int":"0","Owner":null,"Trail":"0"},"0D27":{"Country":"Unknown or unassigned co","Int":"0","Owner":null,"Trail":"0"},"0D5B":{"Country":"Unknown or unassigned co","Int":"0","Owner":null,"Trail":"0"},"0D8C":{"Country":"Unknown or unassigned co","Int":"0","Owner":null,"Trail":"0"},"0DDC":{"Country":"Unknown or unassigned co","Int":"0","Owner":null,"Trail":"0"},"0DF6":{"Country":"Unknown or unassigned co","Int":"0","Owner":null,"Trail":"0"},"0DF7":{"Country":"Unknown or unassigned co","Int":"0","Owner":null,"Trail":"0"},"0E37":{"Country":"Unknown or unassigned co","Int":"0","Owner":null,"Trail":"0"},"0E38":{"Country":"Unknown or unassigned co","Int":"0","Owner":null,"Trail":"0"},"0E5A":{"Country":"Unknown or unassigned co","Int":"0","Owner":null,"Trail":"0"},"0E75":{"Country":"Unknown or unassigned co","Int":"0","Owner":null,"Trail":"0"},"0E8C":{"Country":"Unknown or unassigned co","Int":"0","Owner":null,"Trail":"0"},"0E90":{"Country":"Unknown or unassigned co","Int":"0","Owner":null,"Trail":"0"},"0EFB":{"Country":"Unknown or unassigned co","Int":"0","Owner":null,"Trail":"0"},"0EFC":{"Country":"Unknown or unassigned co","Int":"0","Owner":null,"Trail":"0"},"0F01":{"Country":"Unknown or unassigned co","Int":"0","Owner":null,"Trail":"0"},"0F0B":{"Country":"Unknown or unassigned co","Int":"0","Owner":null,"Trail":"0"},"0FBA":{"Country":"Unknown or unassigned co","Int":"0","Owner":null,"Trail":"0"},"0FC3":{"Country":"Unknown or unassigned co","Int":"0","Owner":null,"Trail":"0"},"0FDD":{"Country":"Unknown or unassigned co","Int":"0","Owner":null,"Trail":"0"},"0FF2":{"Country":"Unknown or unassigned co","Int":"0","Owner":null,"Trail":"0"},"0FF3":{"Country":"Unknown or unassigned co","Int":"0","Owner":null,"Trail":"0"},"100A":{"Country":"Kyrgyzstan","Int":"0","Owner":null,"Trail":"0"},"104F":{"Country":"Kyrgyzstan","Int":"0","Owner":null,"Trail":"0"},"1054":{"Country":"Kyrgyzstan","Int":"0","Owner":null,"Trail":"0"},"1079":{"Country":"Kyrgyzstan","Int":"0","Owner":null,"Trail":"0"},"1097":{"Country":"Kyrgyzstan","Int":"0","Op":"AVJ","Owner":null,"Trail":"0","Type":"Boeing 737","r":"EX-37008"},"10A3":{"Country":"Kyrgyzstan","Int":"0","Owner":null,"Trail":"0"},"10C4":{"Country":"Kyrgyzstan","Int":"0","Owner":null,"Trail":"0"},"10EE":{"Country":"Kyrgyzstan","Int":"0","Owner":null,"Trail":"0"},"10F2":{"Country":"Kyrgyzstan","Image":"2Jet","Int":"0","Op":"EAA","Owner":null,"Short":"A320","Trail":"0","Type":"Airbus A320-212","r":"EX-32001","t":"A320"},"10F4":{"Country":"Kyrgyzstan","Image":"2Jet","Int":"0","Op":"KGA","Owner":null,"Short":"B737-300","Trail":"0","Type":"Boeing 737-301","r":"EX-37001","t":"B733"},"10F9":{"Country":"Kyrgyzstan","Image":"2Jet","Int":"0","Op":"LYN","Owner":null,"Short":"B737-400","Trail":"0","Type":"Boeing 737-484","r":"EX-73401","t":"B734"},"10FD":{"Country":"Kyrgyzstan","Image":"2Jet","Int":"0","Owner":null,"Short":"A320","Trail":"0","r":"EX-32003","t":"A320"},"1100":{"Country":"Kyrgyzstan","Image":"2Jet","Int":"0","Op":"AVJ","Owner":null,"Short":"B737-300","Trail":"0","Type":"Boeing 737 3L9","r":"EX-37010","t":"B733"},"114C":{"Country":"Kyrgyzstan","Int":"0","Owner":null,"Trail":"0"},"1153":{"Country":"Kyrgyzstan","Int":"0","Owner":null,"Trail":"0"},"134E":{"Country":"Kyrgyzstan","Int":"0","Owner":null,"Trail":"0"},"1353":{"Country":"Kyrgyzstan","Int":"0","Owner":null,"Trail":"0"},"1374":{"Country":"Kyrgyzstan","Int":"0","Owner":null,"Trail":"0"},"138D":{"Country":"Kyrgyzstan","Int":"0","Owner":null,"Trail":"0"},"13B1":{"Country":"Kyrgyzstan","Int":"0","Owner":null,"Trail":"0"},"1832":{"Int":"0","Owner":null,"Trail":"0"},"1833":{"Int":"0","Owner":null,"Trail":"0"},"1834":{"Country":"Turkmenistan","Image":"2Jet","Int":"0","Op":"TUA","Owner":null,"Short":"B737-800","Trail":"0","Type":"Boeing 737NG 82K/W","r":"EZ-A018","t":"B738"},"1839":{"Country":"Turkmenistan","Image":"2Jet","Int":"0","Op":"TUA","Owner":null,"Short":"B777-200","Trail":"0","Type":"Boeing 777 22KLR","r":"EZ-A779","t":"B772"},"183A":{"Country":"Turkmenistan","Image":"2Jet","Int":"0","Op":"TUA","Owner":null,"Short":"B777","Trail":"0","Type":"Boeing 777 22KLR","r":"EZ-A778","t":"B772"},"183B":{"Country":"Turkmenistan","Image":"2Jet","Int":"0","Op":"TUA","Owner":null,"Short":"B737-800","Trail":"0","Type":"Boeing 737NG 82K/W","r":"EZ-A017","t":"B738"},"183C":{"Country":"Turkmenistan","Image":"2Jet","Int":"0","Op":"TUA","Owner":null,"Short":"B737-800","Trail":"0","Type":"Boeing 737NG 82K/W","r":"EZ-A016","t":"B738"},"183D":{"Country":"Turkmenistan","Image":"2Jet","Int":"0","Op":"TUA","Owner":null,"Short":"B737-800","Trail":"0","Type":"Boeing 737NG 82K/W","r":"EZ-A015","t":"B738"},"1841":{"Country":"Turkmenistan","Int":"0","Owner":null,"Trail":"0"},"1842":{"Country":"Turkmenistan","Image":"2Jet","Int":"0","Op":"TUA","Owner":null,"Short":"B757-200","Trail":"0","Type":"Boeing 757-23A","r":"EZ-A010","t":"B752"},"1846":{"Country":"Turkmenistan","Image":"2Jet","Int":"0","Op":"TUA","Owner":null,"Short":"B757-200","Trail":"0","Type":"Boeing 757 22K","r":"EZ-A011","t":"B752"},"1847":{"Country":"Turkmenistan","Image":"2Jet","Int":"0","Op":"TUA","Owner":null,"Short":"B757-200","Trail":"0","Type":"Boeing 757-22K","r":"EZ-A012","t":"B752"},"1849":{"Country":"Turkmenistan","Image":"2Jet","Int":"0","Op":"TUA","Owner":null,"Short":"B757-200","Trail":"0","Type":"Boeing 757 22K","r":"EZ-A014","t":"B752"},"1854":{"Country":"Turkmenistan","Image":"2Jet","Int":"0","Op":"TUA","Owner":null,"Short":"B717-200","Trail":"0","Type":"Boeing 717-22K","r":"EZ-A106","t":"B712"},"1855":{"Country":"Turkmenistan","Image":"2Jet","Int":"0","Op":"TUA","Owner":null,"Short":"B717-200","Trail":"0","Type":"Boeing 717-22K","r":"EZ-A107","t":"B712"},"1856":{"Country":"Turkmenistan","Int":"0","Owner":null,"Trail":"0"},"1857":{"Country":"Turkmenistan","Image":"Heli","Int":"1","Owner":null,"Short":"Sikorsky","Trail":"5","Type":"Sikorsky S-92 A","r":"EZ-S721","t":"S92"},"1858":{"Country":"Turkmenistan","Image":"2Jet","Int":"0","Op":"TUA","Owner":null,"Short":"B737-800","Trail":"0","Type":"Boeing 737NG 82K/W","r":"EZ-A004","t":"B738"},"1859":{"Country":"Turkmenistan","Image":"2Jet","Int":"0","Op":"TUA","Owner":null,"Short":"B737-800","Trail":"0","Type":"Boeing 737NG 82K/W","r":"EZ-A005","t":"B738"},"185A":{"Country":"Turkmenistan","Image":"2Jet","Int":"1","Op":"TUA","Owner":null,"Short":"B737-700","Trail":"5","Type":"Boeing 737NG 7GL/W","r":"EZ-A007","t":"B737"},"185B":{"Country":"Turkmenistan","Int":"0","Owner":null,"Trail":"0"},"185E":{"Country":"Turkmenistan","Image":"2Jet","Int":"0","Op":"TUA","Owner":null,"Short":"B737-700","Trail":"0","Type":"Boeing 737-7GL/W","r":"EZ-A006","t":"B737"},"185F":{"Country":"Turkmenistan","Image":"2Jet","Int":"0","Op":"TUA","Owner":null,"Short":"B737-700","Trail":"0","Type":"Boeing 737-7GL/W","r":"EZ-A008","t":"B737"},"1860":{"Country":"Turkmenistan","Image":"2Jet","Int":"0","Op":"TUA","Owner":null,"Short":"B737-700","Trail":"0","Type":"Boeing 737NG 7GL/W","r":"EZ-A009","t":"B737"},"1861":{"Country":"Turkmenistan","Image":"2Jet","Int":"1","Op":"TUA","Owner":null,"Short":"B777-200","Trail":"5","Type":"Boeing 777 22KLR","r":"EZ-A777","t":"B772"},"1862":{"Country":"Turkmenistan","Image":"Heli","Int":"1","Owner":null,"Short":"Merlin","Trail":"5","Type":"EH Industries EH.101 Merlin Mk.643","r":"EZ-S714","t":"EH10"},"1BDF":{"Country":"Turkmenistan","Int":"0","Owner":null,"Trail":"0"},"1C00":{"Int":"0","Owner":null,"Trail":"0"},"1DAD":{"Int":"0","Owner":null,"Trail":"0"},"2A93":{"Country":"Unknown or unassigned co","Int":"0","Owner":null,"Trail":"0"},"2B78":{"Country":"Unknown or unassigned co","Int":"0","Owner":null,"Trail":"0"},"2C36":{"Country":"Unknown or unassigned co","Int":"0","Owner":null,"Trail":"0"},"36A1":{"Int":"0","Owner":null,"Trail":"0"},"3874":{"Country":"Unknown or unassigned co","Int":"0","Owner":null,"Trail":"0"},"39E0":{"Country":"Unknown or unassigned co","Int":"0","Owner":null,"Trail":"0"},"3A2A":{"Country":"Unknown or unassigned co","Int":"0","Owner":null,"Trail":"0"},"3B74":{"Country":"Unknown or unassigned co","Int":"0","Owner":null,"Trail":"0"},"3B75":{"Country":"Unknown or unassigned co","Int":"0","Owner":null,"Trail":"0"},"3F74":{"Country":"Unknown or unassigned co","Int":"0","Owner":null,"Trail":"0"},"3F7F":{"Country":"Unknown or unassigned co","Int":"0","Owner":null,"Trail":"0"},"4078":{"Country":"Unknown or unassigned co","Int":"0","Owner":null,"Trail":"0"},"4574":{"Country":"Unknown or unassigned co","Int":"0","Owner":null,"Trail":"0"},"46AE":{"Country":"Unknown or unassigned co","Int":"0","Owner":null,"Trail":"0"},"4A0A":{"Country":"Unknown or unassigned co","Int":"0","Owner":null,"Trail":"0"},"4B4D":{"Country":"Unknown or unassigned co","Int":"0","Owner":null,"Trail":"0"},"4C00":{"Country":"Unknown or unassigned co","Int":"0","Owner":null,"Trail":"0"},"53C4":{"Country":"Unknown or unassigned co","Int":"0","Owner":null,"Trail":"0"},"543F":{"Country":"Unknown or unassigned co","Int":"0","Owner":null,"Trail":"0"},"5518":{"Int":"0","Owner":null,"Trail":"0"},"55B4":{"Country":"Unknown or unassigned co","Int":"0","Owner":null,"Trail":"0"},"5636":{"Country":"Unknown or unassigned co","Int":"0","Owner":null,"Trail":"0"},"5637":{"Country":"Unknown or unassigned co","Int":"0","Owner":null,"Trail":"0"},"5958":{"Country":"Unknown or unassigned co","Int":"0","Owner":null,"Trail":"0"},"5B77":{"Country":"Unknown or unassigned co","Int":"0","Owner":null,"Trail":"0"},"5BFE":{"Country":"Unknown or unassigned co","Int":"0","Owner":null,"Trail":"0"},"5C03":{"Country":"Unknown or unassigned co","Int":"0","Owner":null,"Trail":"0"},"5C04":{"Country":"Unknown or unassigned co","Int":"0","Owner":null,"Trail":"0"},"5CC2":{"Country":"Unknown or unassigned co","Int":"0","Owner":null,"Trail":"0"},"5D0E":{"Country":"Unknown or unassigned co","Int":"0","Owner":null,"Trail":"0"},"5DEA":{"Country":"Unknown or unassigned co","Int":"0","Owner":null,"Trail":"0"},"5E24":{"Country":"Unknown or unassigned co","Int":"0","Owner":null,"Trail":"0"},"5E53":{"Country":"Unknown or unassigned co","Int":"0","Owner":null,"Trail":"0"},"5E66":{"Country":"Unknown or unassigned co","Int":"0","Owner":null,"Trail":"0"},"5F79":{"Country":"Unknown or unassigned co","Int":"0","Owner":null,"Trail":"0"},"5FB6":{"Country":"Unknown or unassigned co","Int":"0","Owner":null,"Trail":"0"},"5FD5":{"Country":"Unknown or unassigned co","Int":"0","Owner":null,"Trail":"0"},"6016":{"Country":"Unknown or unassigned co","Int":"0","Owner":null,"Trail":"0"},"604B":{"Country":"Unknown or unassigned co","Int":"0","Owner":null,"Trail":"0"},"6090":{"Country":"Unknown or unassigned co","Int":"0","Owner":null,"Trail":"0"},"60A5":{"Country":"Unknown or unassigned co","Int":"0","Owner":null,"Trail":"0"},"6130":{"Country":"Unknown or unassigned co","Int":"0","Owner":null,"Trail":"0"},"6135":{"Country":"Unknown or unassigned co","Int":"0","Owner":null,"Trail":"0"},"622D":{"Country":"Unknown or unassigned co","Int":"0","Owner":null,"Trail":"0"},"631C":{"Country":"Unknown or unassigned co","Int":"0","Owner":null,"Trail":"0"},"6321":{"Country":"Unknown or unassigned co","Int":"0","Owner":null,"Trail":"0"},"643B":{"Country":"Unknown or unassigned co","Int":"0","Owner":null,"Trail":"0"},"6443":{"Country":"Unknown or unassigned co","Int":"0","Owner":null,"Trail":"0"},"647F":{"Country":"Unknown or unassigned co","Int":"0","Owner":null,"Trail":"0"},"64A1":{"Country":"Unknown or unassigned co","Int":"0","Owner":null,"Trail":"0"},"655D":{"Country":"Unknown or unassigned co","Int":"0","Owner":null,"Trail":"0"},"659A":{"Country":"Unknown or unassigned co","Int":"0","Owner":null,"Trail":"0"},"65A8":{"Country":"Unknown or unassigned co","Int":"0","Owner":null,"Trail":"0"},"660C":{"Country":"Unknown or unassigned co","Int":"0","Owner":null,"Trail":"0"},"660E":{"Country":"Unknown or unassigned co","Int":"0","Owner":null,"Trail":"0"},"665E":{"Country":"Unknown or unassigned co","Int":"0","Owner":null,"Trail":"0"},"665F":{"Country":"Unknown or unassigned co","Int":"0","Owner":null,"Trail":"0"},"6660":{"Country":"Unknown or unassigned co","Int":"0","Owner":null,"Trail":"0"},"6667":{"Country":"Unknown or unassigned co","Int":"0","Owner":null,"Trail":"0"},"6668":{"Country":"Unknown or unassigned co","Int":"0","Owner":null,"Trail":"0"},"6669":{"Country":"Unknown or unassigned co","Int":"0","Owner":null,"Trail":"0"},"666B":{"Country":"Unknown or unassigned co","Int":"0","Owner":null,"Trail":"0"},"66B9":{"Country":"Unknown or unassigned co","Int":"0","Owner":null,"Trail":"0"},"66CD":{"Country":"Unknown or unassigned co","Int":"0","Owner":null,"Trail":"0"},"66CE":{"Country":"Unknown or unassigned co","Int":"0","Owner":null,"Trail":"0"},"66CF":{"Country":"Unknown or unassigned co","Int":"0","Owner":null,"Trail":"0"},"66D1":{"Country":"Unknown or unassigned co","Int":"0","Owner":null,"Trail":"0"},"66F7":{"Country":"Unknown or unassigned co","Int":"0","Owner":null,"Trail":"0"},"6745":{"Country":"Unknown or unassigned co","Int":"0","Owner":null,"Trail":"0"},"6755":{"Country":"Unknown or unassigned co","Int":"0","Owner":null,"Trail":"0"},"67F0":{"Country":"Unknown or unassigned co","Int":"0","Owner":null,"Trail":"0"},"67F1":{"Country":"Unknown or unassigned co","Int":"0","Owner":null,"Trail":"0"},"67F3":{"Country":"Unknown or unassigned co","Int":"0","Owner":null,"Trail":"0"},"67F4":{"Country":"Unknown or unassigned co","Int":"0","Owner":null,"Trail":"0"},"67F6":{"Country":"Unknown or unassigned co","Int":"0","Owner":null,"Trail":"0"},"67F7":{"Country":"Unknown or unassigned co","Int":"0","Owner":null,"Trail":"0"},"67F8":{"Country":"Unknown or unassigned co","Int":"0","Owner":null,"Trail":"0"},"6811":{"Country":"Unknown or unassigned co","Int":"0","Owner":null,"Trail":"0"},"6814":{"Country":"Unknown or unassigned co","Int":"0","Owner":null,"Trail":"0"},"6824":{"Country":"Unknown or unassigned co","Int":"0","Owner":null,"Trail":"0"},"6863":{"Country":"Unknown or unassigned co","Int":"0","Owner":null,"Trail":"0"},"68B4":{"Country":"Unknown or unassigned co","Int":"0","Owner":null,"Trail":"0"},"68B5":{"Country":"Unknown or unassigned co","Int":"0","Owner":null,"Trail":"0"},"68B7":{"Country":"Unknown or unassigned co","Int":"0","Owner":null,"Trail":"0"},"68CB":{"Country":"Unknown or unassigned co","Int":"0","Owner":null,"Trail":"0"},"68F6":{"Country":"Unknown or unassigned co","Int":"0","Owner":null,"Trail":"0"},"6900":{"Country":"Unknown or unassigned co","Int":"0","Owner":null,"Trail":"0"},"6905":{"Country":"Unknown or unassigned co","Int":"0","Owner":null,"Trail":"0"},"6909":{"Country":"Unknown or unassigned co","Int":"0","Owner":null,"Trail":"0"},"695B":{"Country":"Unknown or unassigned co","Int":"0","Owner":null,"Trail":"0"},"6A4F":{"Country":"Unknown or unassigned co","Int":"0","Owner":null,"Trail":"0"},"6A63":{"Country":"Unknown or unassigned co","Int":"0","Owner":null,"Trail":"0"},"6AC3":{"Country":"Unknown or unassigned co","Int":"0","Owner":null,"Trail":"0"},"6AC4":{"Country":"Unknown or unassigned co","Int":"0","Owner":null,"Trail":"0"},"7518":{"Int":"0","Owner":null,"Trail":"0"},"7A1C":{"Country":"Unknown or unassigned co","Int":"0","Owner":null,"Trail":"0"},"90A8":{"Country":"Unknown or unassigned co","Int":"0","Owner":null,"Trail":"0"},"916E":{"Country":"Unknown or unassigned co","Int":"0","Owner":null,"Trail":"0"},"9191":{"Country":"Unknown or unassigned co","Int":"0","Owner":null,"Trail":"0"},"9286":{"Country":"Unknown or unassigned co","Int":"0","Owner":null,"Trail":"0"},"92E4":{"Country":"Unknown or unassigned co","Int":"0","Owner":null,"Trail":"0"},"9626":{"Country":"Unknown or unassigned co","Int":"0","Owner":null,"Trail":"0"},"9627":{"Country":"Unknown or unassigned co","Int":"0","Owner":null,"Trail":"0"},"9652":{"Country":"Unknown or unassigned co","Int":"0","Owner":null,"Trail":"0"},"970E":{"Country":"Unknown or unassigned co","Int":"0","Owner":null,"Trail":"0"},"990E":{"Country":"Unknown or unassigned co","Int":"0","Owner":null,"Trail":"0"},"9942":{"Country":"Unknown or unassigned co","Int":"0","Owner":null,"Trail":"0"},"9986":{"Country":"Unknown or unassigned co","Int":"0","Owner":null,"Trail":"0"},"9AA8":{"Country":"Unknown or unassigned co","Int":"0","Owner":null,"Trail":"0"},"9AF2":{"Country":"Unknown or unassigned co","Int":"0","Owner":null,"Trail":"0"},"9C5B":{"Country":"Unknown or unassigned co","Int":"0","Owner":null,"Trail":"0"},"9DD2":{"Country":"Unknown or unassigned co","Int":"0","Owner":null,"Trail":"0"},"9F15":{"Country":"Unknown or unassigned co","Int":"0","Owner":null,"Trail":"0"},"9F87":{"Country":"Unknown or unassigned co","Int":"0","Owner":null,"Trail":"0"},"A2D8":{"Country":"Unknown or unassigned co","Int":"0","Owner":null,"Trail":"0"},"A523":{"Country":"Unknown or unassigned co","Int":"0","Owner":null,"Trail":"0"},"A5E3":{"Country":"Unknown or unassigned co","Int":"0","Owner":null,"Trail":"0"},"A8D6":{"Int":"0","Owner":null,"Trail":"0"},"AD6A":{"Country":"Unknown or unassigned co","Int":"0","Owner":null,"Trail":"0"},"AD6B":{"Country":"Unknown or unassigned co","Int":"0","Owner":null,"Trail":"0"},"ADC8":{"Country":"Unknown or unassigned co","Int":"0","Owner":null,"Trail":"0"},"B3B5":{"Country":"Unknown or unassigned co","Int":"0","Owner":null,"Trail":"0"},"B503":{"Country":"Unknown or unassigned co","Int":"0","Owner":null,"Trail":"0"},"B602":{"Country":"Unknown or unassigned co","Int":"0","Owner":null,"Trail":"0"},"BD7D":{"Int":"0","Owner":null,"Trail":"0"},"BF41":{"Country":"Unknown or unassigned co","Int":"0","Owner":null,"Trail":"0"},"C126":{"Country":"Unknown or unassigned co","Int":"0","Owner":null,"Trail":"0"},"C127":{"Country":"Unknown or unassigned co","Int":"0","Owner":null,"Trail":"0"},"C2CB":{"Country":"Unknown or unassigned co","Int":"0","Owner":null,"Trail":"0"},"C426":{"Country":"Unknown or unassigned co","Int":"0","Owner":null,"Trail":"0"},"C626":{"Country":"Unknown or unassigned co","Int":"0","Owner":null,"Trail":"0"},"C663":{"Country":"Unknown or unassigned co","Int":"0","Owner":null,"Trail":"0"},"C784":{"Country":"Unknown or unassigned co","Int":"0","Owner":null,"Trail":"0"},"D1A7":{"Country":"Unknown or unassigned co","Int":"0","Owner":null,"Trail":"0"},"D786":{"Country":"Unknown or unassigned co","Int":"0","Owner":null,"Trail":"0"},"D86A":{"Country":"Unknown or unassigned co","Int":"0","Owner":null,"Trail":"0"},"EAEC":{"Country":"Unknown or unassigned co","Int":"0","Owner":null,"Trail":"0"},"FD5C":{"Country":"Unknown or unassigned co","Int":"0","Owner":null,"Trail":"0"},"FD5D":{"Country":"Unknown or unassigned co","Int":"0","Owner":null,"Trail":"0"},"FF0B":{"Int":"0","Owner":null,"Trail":"0"}}