{"011D":{"Image":"Missing","Int":"0","Owner":null,"Trail":"0"},"0294":{"Image":"Missing","Int":"0","Owner":null,"Trail":"0"},"0297":{"Image":"Missing","Int":"0","Owner":null,"Trail":"0"},"02D9":{"Image":"Missing","Int":"0","Owner":null,"Trail":"0"},"038C":{"Image":"Missing","Int":"0","Owner":null,"Trail":"0"},"03A6":{"Image":"Missing","Int":"0","Owner":null,"Trail":"0"},"0408":{"Image":"Missing","Int":"0","Owner":null,"Trail":"0"},"057F":{"Image":"Missing","Int":"0","Owner":null,"Trail":"0"},"05C5":{"Image":"Missing","Int":"0","Owner":null,"Trail":"0"},"07A9":{"Image":"Missing","Int":"0","Owner":null,"Trail":"0"},"07E4":{"Image":"Missing","Int":"0","Owner":null,"Trail":"0"},"0887":{"Image":"Missing","Int":"0","Owner":null,"Trail":"0"},"08CF":{"Image":"Missing","Int":"0","Owner":null,"Trail":"0"},"095B":{"Image":"Missing","Int":"0","Owner":null,"Trail":"0"},"096D":{"Image":"Missing","Int":"0","Owner":null,"Trail":"0"},"0996":{"Image":"Missing","Int":"0","Owner":null,"Trail":"0"},"0A9D":{"Image":"Missing","Int":"0","Owner":null,"Trail":"0"},"0AE2":{"Image":"Missing","Int":"0","Owner":null,"Trail":"0"},"0B05":{"Image":"Missing","Int":"0","Owner":null,"Trail":"0"},"0BA0":{"Image":"Missing","Int":"0","Owner":null,"Trail":"0"},"0C6F":{"Image":"Missing","Int":"0","Owner":null,"Trail":"0"},"0CA9":{"Image":"Missing","Int":"0","Owner":null,"Trail":"0"},"0CD9":{"Image":"Missing","Int":"0","Owner":null,"Trail":"0"},"0CED":{"Image":"Missing","Int":"0","Owner":null,"Trail":"0"},"0D00":{"Image":"Missing","Int":"0","Owner":null,"Trail":"0"},"0DA7":{"Image":"Missing","Int":"0","Owner":null,"Trail":"0"},"0DB1":{"Image":"Missing","Int":"0","Owner":null,"Trail":"0"},"0DB6":{"Image":"Missing","Int":"0","Owner":null,"Trail":"0"},"0FBF":{"Image":"Missing","Int":"0","Owner":null,"Trail":"0"},"1040":{"Image":"Missing","Int":"0","Owner":null,"Trail":"0"},"1067":{"Image":"Missing","Int":"0","Owner":null,"Trail":"0"},"107B":{"Image":"Missing","Int":"0","Owner":null,"Trail":"0"},"107C":{"Image":"Missing","Int":"0","Owner":null,"Trail":"0"},"1080":{"Image":"Missing","Int":"0","Owner":null,"Trail":"0"},"1098":{"Image":"Missing","Int":"0","Owner":null,"Trail":"0"},"109C":{"Image":"Missing","Int":"0","Owner":null,"Trail":"0"},"10E4":{"Image":"Missing","Int":"0","Owner":null,"Trail":"0"},"1132":{"Image":"Missing","Int":"0","Owner":null,"Trail":"0"},"1156":{"Image":"Missing","Int":"0","Owner":null,"Trail":"0"},"117C":{"Image":"Missing","Int":"0","Owner":null,"Trail":"0"},"1281":{"Image":"Missing","Int":"0","Owner":null,"Trail":"0"},"12AE":{"Image":"Missing","Int":"0","Owner":null,"Trail":"0"},"12D1":{"Image":"Missing","Int":"0","Owner":null,"Trail":"0"},"12D4":{"Image":"Missing","Int":"0","Owner":null,"Trail":"0"},"130A":{"Image":"Missing","Int":"0","Owner":null,"Trail":"0"},"133E":{"Image":"Missing","Int":"0","Owner":null,"Trail":"0"},"1377":{"Image":"Missing","Int":"0","Owner":null,"Trail":"0"},"137E":{"Image":"Missing","Int":"0","Owner":null,"Trail":"0"},"13AF":{"Image":"Missing","Int":"0","Owner":null,"Trail":"0"},"13B7":{"Image":"Missing","Int":"0","Owner":null,"Trail":"0"},"13D7":{"Image":"Missing","Int":"0","Owner":null,"Trail":"0"},"145D":{"Image":"Missing","Int":"0","Owner":null,"Trail":"0"},"1479":{"Image":"Missing","Int":"0","Owner":null,"Trail":"0"},"1530":{"Image":"Missing","Int":"0","Owner":null,"Trail":"0"},"1658":{"Image":"Missing","Int":"0","Owner":null,"Trail":"0"},"16D9":{"Image":"Missing","Int":"0","Owner":null,"Trail":"0"},"1706":{"Image":"Missing","Int":"0","Owner":null,"Trail":"0"},"18B3":{"Image":"Missing","Int":"0","Owner":null,"Trail":"0"},"18F9":{"Image":"Missing","Int":"0","Owner":null,"Trail":"0"},"191F":{"Image":"Missing","Int":"0","Owner":null,"Trail":"0"},"1946":{"Image":"Missing","Int":"0","Owner":null,"Trail":"0"},"1AE8":{"Image":"Missing","Int":"0","Owner":null,"Trail":"0"},"1B63":{"Image":"Missing","Int":"0","Owner":null,"Trail":"0"},"1C48":{"Image":"Missing","Int":"0","Owner":null,"Trail":"0"},"1C5A":{"Image":"Missing","Int":"0","Owner":null,"Trail":"0"},"1CAE":{"Image":"Missing","Int":"0","Owner":null,"Trail":"0"},"1CD8":{"Image":"Missing","Int":"0","Owner":null,"Trail":"0"},"1D21":{"Image":"Missing","Int":"0","Owner":null,"Trail":"0"},"1D47":{"Image":"Missing","Int":"0","Owner":null,"Trail":"0"},"1D57":{"Image":"Missing","Int":"0","Owner":null,"Trail":"0"},"1DB8":{"Image":"Missing","Int":"0","Owner":null,"Trail":"0"},"1E18":{"Image":"Missing","Int":"0","Owner":null,"Trail":"0"},"1F48":{"Image":"Missing","Int":"0","Owner":null,"Trail":"0"},"1FBE":{"Image":"Missing","Int":"0","Owner":null,"Trail":"0"},"1FDC":{"Image":"Missing","Int":"0","Owner":null,"Trail":"0"},"1FE9":{"Image":"Missing","Int":"0","Owner":null,"Trail":"0"},"1FFB":{"Image":"Missing","Int":"0","Owner":null,"Trail":"0"},"2019":{"Image":"Missing","Int":"0","Owner":null,"Trail":"0"},"201B":{"Image":"Missing","Int":"0","Owner":null,"Trail":"0"},"207D":{"Image":"Missing","Int":"0","Owner":null,"Trail":"0"},"20C8":{"Image":"Missing","Int":"0","Owner":null,"Trail":"0"},"20CC":{"Image":"Missing","Int":"0","Owner":null,"Trail":"0"},"210D":{"Image":"Missing","Int":"0","Owner":null,"Trail":"0"},"2111":{"Image":"Missing","Int":"0","Owner":null,"Trail":"0"},"2172":{"Image":"Missing","Int":"0","Owner":null,"Trail":"0"},"2175":{"Image":"Missing","Int":"0","Owner":null,"Trail":"0"},"2187":{"Image":"Missing","Int":"0","Owner":null,"Trail":"0"},"21BE":{"Image":"Missing","Int":"0","Owner":null,"Trail":"0"},"21C2":{"Image":"Missing","Int":"0","Owner":null,"Trail":"0"},"21C4":{"Image":"Missing","Int":"0","Owner":null,"Trail":"0"},"21C6":{"Image":"Missing","Int":"0","Owner":null,"Trail":"0"},"21E4":{"Image":"Missing","Int":"0","Owner":null,"Trail":"0"},"21EA":{"Image":"Missing","Int":"0","Owner":null,"Trail":"0"},"2209":{"Image":"Missing","Int":"0","Owner":null,"Trail":"0"},"2285":{"Image":"Missing","Int":"0","Owner":null,"Trail":"0"},"2292":{"Image":"Missing","Int":"0","Owner":null,"Trail":"0"},"22C4":{"Image":"Missing","Int":"0","Owner":null,"Trail":"0"},"22C9":{"Image":"Missing","Int":"0","Owner":null,"Trail":"0"},"22CD":{"Image":"Missing","Int":"0","Owner":null,"Trail":"0"},"22D9":{"Image":"Missing","Int":"0","Owner":null,"Trail":"0"},"22DD":{"Image":"Missing","Int":"0","Owner":null,"Trail":"0"},"22ED":{"Image":"Missing","Int":"0","Owner":null,"Trail":"0"},"2339":{"Image":"Missing","Int":"0","Owner":null,"Trail":"0"},"23AC":{"Image":"Missing","Int":"0","Owner":null,"Trail":"0"},"23C8":{"Image":"Missing","Int":"0","Owner":null,"Trail":"0"},"244C":{"Image":"Missing","Int":"0","Owner":null,"Trail":"0"},"2481":{"Image":"Missing","Int":"0","Owner":null,"Trail":"0"},"24A4":{"Image":"Missing","Int":"0","Owner":null,"Trail":"0"},"24A9":{"Image":"Missing","Int":"0","Owner":null,"Trail":"0"},"24EB":{"Image":"Missing","Int":"0","Owner":null,"Trail":"0"},"24ED":{"Image":"Missing","Int":"0","Owner":null,"Trail":"0"},"24EF":{"Image":"Missing","Int":"0","Owner":null,"Trail":"0"},"2509":{"Image":"Missing","Int":"0","Owner":null,"Trail":"0"},"250F":{"Image":"Missing","Int":"0","Owner":null,"Trail":"0"},"252C":{"Image":"Missing","Int":"0","Owner":null,"Trail":"0"},"2609":{"Image":"Missing","Int":"0","Owner":null,"Trail":"0"},"2663":{"Image":"Missing","Int":"0","Owner":null,"Trail":"0"},"2667":{"Image":"Missing","Int":"0","Owner":null,"Trail":"0"},"2673":{"Image":"Missing","Int":"0","Owner":null,"Trail":"0"},"2677":{"Image":"Missing","Int":"0","Owner":null,"Trail":"0"},"27A7":{"Image":"Missing","Int":"0","Owner":null,"Trail":"0"},"27B3":{"Image":"Missing","Int":"0","Owner":null,"Trail":"0"},"27B7":{"Image":"Missing","Int":"0","Owner":null,"Trail":"0"},"2823":{"Image":"Missing","Int":"0","Owner":null,"Trail":"0"},"2825":{"Image":"Missing","Int":"0","Owner":null,"Trail":"0"},"2828":{"Image":"Missing","Int":"0","Owner":null,"Trail":"0"},"2EAF":{"Image":"Missing","Int":"0","Owner":null,"Trail":"0"},"2EBB":{"Image":"Missing","Int":"0","Owner":null,"Trail":"0"},"2EC2":{"Image":"Missing","Int":"0","Owner":null,"Trail":"0"},"2F93":{"Image":"Missing","Int":"0","Owner":null,"Trail":"0"},"3017":{"Image":"Missing","Int":"0","Owner":null,"Trail":"0"},"3019":{"Image":"Missing","Int":"0","Owner":null,"Trail":"0"},"301B":{"Image":"Missing","Int":"0","Owner":null,"Trail":"0"},"3050":{"Image":"Missing","Int":"0","Owner":null,"Trail":"0"},"3051":{"Image":"Missing","Int":"0","Owner":null,"Trail":"0"},"3079":{"Image":"Missing","Int":"0","Owner":null,"Trail":"0"},"308A":{"Image":"Missing","Int":"0","Owner":null,"Trail":"0"},"309A":{"Image":"Missing","Int":"0","Owner":null,"Trail":"0"},"30BB":{"Image":"Missing","Int":"0","Owner":null,"Trail":"0"},"30CA":{"Image":"Missing","Int":"0","Owner":null,"Trail":"0"},"30E9":{"Image":"Missing","Int":"0","Owner":null,"Trail":"0"},"318A":{"Image":"Missing","Int":"0","Owner":null,"Trail":"0"},"31CA":{"Image":"Missing","Int":"0","Owner":null,"Trail":"0"},"325C":{"Image":"Missing","Int":"0","Owner":null,"Trail":"0"},"327B":{"Image":"Missing","Int":"0","Owner":null,"Trail":"0"},"32DD":{"Image":"Missing","Int":"0","Owner":null,"Trail":"0"},"3332":{"Image":"Missing","Int":"0","Owner":null,"Trail":"0"},"34A0":{"Image":"Missing","Int":"0","Owner":null,"Trail":"0"},"3617":{"Image":"Missing","Int":"0","Owner":null,"Trail":"0"},"3638":{"Image":"Missing","Int":"0","Owner":null,"Trail":"0"},"3734":{"Image":"Missing","Int":"0","Owner":null,"Trail":"0"},"379E":{"Image":"Missing","Int":"0","Owner":null,"Trail":"0"},"37B0":{"Image":"Missing","Int":"0","Owner":null,"Trail":"0"},"3828":{"Image":"Missing","Int":"0","Owner":null,"Trail":"0"},"398B":{"Image":"Missing","Int":"0","Owner":null,"Trail":"0"},"3A52":{"Image":"Missing","Int":"0","Owner":null,"Trail":"0"},"3B28":{"Image":"Missing","Int":"0","Owner":null,"Trail":"0"},"3C25":{"Image":"Missing","Int":"0","Owner":null,"Trail":"0"},"3C8B":{"Image":"Missing","Int":"0","Owner":null,"Trail":"0"},"3E3C":{"Image":"Missing","Int":"0","Owner":null,"Trail":"0"},"3E3E":{"Image":"Missing","Int":"0","Owner":null,"Trail":"0"},"3EC0":{"Image":"Missing","Int":"0","Owner":null,"Trail":"0"},"3F44":{"Image":"Missing","Int":"0","Owner":null,"Trail":"0"},"3F48":{"Image":"Missing","Int":"0","Owner":null,"Trail":"0"},"3F4E":{"Image":"Missing","Int":"0","Owner":null,"Trail":"0"},"4048":{"Image":"Missing","Int":"0","Owner":null,"Trail":"0"},"4092":{"Image":"Missing","Int":"0","Owner":null,"Trail":"0"},"41D1":{"Image":"Missing","Int":"0","Owner":null,"Trail":"0"},"41EF":{"Image":"Missing","Int":"0","Owner":null,"Trail":"0"},"42CE":{"Int":"0","Owner":null,"Trail":"0"},"42DC":{"Image":"Missing","Int":"0","Owner":null,"Trail":"0"},"437A":{"Image":"Missing","Int":"0","Owner":null,"Trail":"0"},"4381":{"Image":"Missing","Int":"0","Owner":null,"Trail":"0"},"4565":{"Image":"Missing","Int":"0","Owner":null,"Trail":"0"},"45A6":{"Image":"Missing","Int":"0","Owner":null,"Trail":"0"},"45B6":{"Image":"Missing","Int":"0","Owner":null,"Trail":"0"},"45E1":{"Image":"Missing","Int":"0","Owner":null,"Trail":"0"},"4628":{"Image":"Missing","Int":"0","Owner":null,"Trail":"0"},"467A":{"Image":"Missing","Int":"0","Owner":null,"Trail":"0"},"47EE":{"Image":"Missing","Int":"0","Owner":null,"Trail":"0"},"4ACC":{"Image":"Missing","Int":"0","Owner":null,"Trail":"0"},"4ACF":{"Image":"Missing","Int":"0","Owner":null,"Trail":"0"},"4CC9":{"Image":"Missing","Int":"0","Owner":null,"Trail":"0"},"4CDE":{"Image":"Missing","Int":"0","Owner":null,"Trail":"0"},"4DC6":{"Image":"Missing","Int":"0","Owner":null,"Trail":"0"},"4E62":{"Image":"Missing","Int":"0","Owner":null,"Trail":"0"},"4E63":{"Image":"Missing","Int":"0","Owner":null,"Trail":"0"},"4E6B":{"Image":"Missing","Int":"0","Owner":null,"Trail":"0"},"4E70":{"Image":"Missing","Int":"0","Owner":null,"Trail":"0"},"4E80":{"Image":"Missing","Int":"0","Owner":null,"Trail":"0"},"4F06":{"Image":"Missing","Int":"0","Owner":null,"Trail":"0"},"4F20":{"Image":"Missing","Int":"0","Owner":null,"Trail":"0"},"4FDC":{"Image":"Missing","Int":"0","Owner":null,"Trail":"0"},"503B":{"Image":"Missing","Int":"0","Owner":null,"Trail":"0"},"507D":{"Image":"Missing","Int":"0","Owner":null,"Trail":"0"},"51D9":{"Image":"Missing","Int":"0","Owner":null,"Trail":"0"},"51DB":{"Image":"Missing","Int":"0","Owner":null,"Trail":"0"},"51ED":{"Image":"Missing","Int":"0","Owner":null,"Trail":"0"},"51F4":{"Image":"Missing","Int":"0","Owner":null,"Trail":"0"},"52B8":{"Image":"Missing","Int":"0","Owner":null,"Trail":"0"},"5383":{"Image":"Missing","Int":"0","Owner":null,"Trail":"0"},"55E9":{"Image":"Missing","Int":"0","Owner":null,"Trail":"0"},"5877":{"Image":"Missing","Int":"0","Owner":null,"Trail":"0"},"5A05":{"Image":"Missing","Int":"0","Owner":null,"Trail":"0"},"5A3A":{"Image":"Missing","Int":"0","Owner":null,"Trail":"0"},"5B51":{"Image":"Missing","Int":"0","Owner":null,"Trail":"0"},"5B76":{"Image":"Missing","Int":"0","Owner":null,"Trail":"0"},"5C6E":{"Image":"Missing","Int":"0","Owner":null,"Trail":"0"},"5DA1":{"Image":"Missing","Int":"0","Owner":null,"Trail":"0"},"5EA5":{"Image":"Missing","Int":"0","Owner":null,"Trail":"0"},"5F7A":{"Image":"Missing","Int":"0","Owner":null,"Trail":"0"},"6037":{"Image":"Missing","Int":"0","Owner":null,"Trail":"0"},"6039":{"Image":"Missing","Int":"0","Owner":null,"Trail":"0"},"61DB":{"Image":"Missing","Int":"0","Owner":null,"Trail":"0"},"61DD":{"Image":"Missing","Int":"0","Owner":null,"Trail":"0"},"6215":{"Image":"Missing","Int":"0","Owner":null,"Trail":"0"},"62A0":{"Image":"Missing","Int":"0","Owner":null,"Trail":"0"},"6307":{"Image":"Missing","Int":"0","Owner":null,"Trail":"0"},"638D":{"Image":"Missing","Int":"0","Owner":null,"Trail":"0"},"63EB":{"Image":"Missing","Int":"0","Owner":null,"Trail":"0"},"645B":{"Image":"Missing","Int":"0","Owner":null,"Trail":"0"},"64F3":{"Image":"Missing","Int":"0","Owner":null,"Trail":"0"},"6620":{"Image":"Missing","Int":"0","Owner":null,"Trail":"0"},"6626":{"Image":"Missing","Int":"0","Owner":null,"Trail":"0"},"6675":{"Image":"Missing","Int":"0","Owner":null,"Trail":"0"},"672C":{"Image":"Missing","Int":"0","Owner":null,"Trail":"0"},"6735":{"Image":"Missing","Int":"0","Owner":null,"Trail":"0"},"6738":{"Image":"Missing","Int":"0","Owner":null,"Trail":"0"},"683E":{"Image":"Missing","Int":"0","Owner":null,"Trail":"0"},"698C":{"Image":"Missing","Int":"0","Owner":null,"Trail":"0"},"69A6":{"Image":"Missing","Int":"0","Owner":null,"Trail":"0"},"69B7":{"Image":"Missing","Int":"0","Owner":null,"Trail":"0"},"6A42":{"Image":"Missing","Int":"0","Owner":null,"Trail":"0"},"6ABE":{"Image":"Missing","Int":"0","Owner":null,"Trail":"0"},"6B1F":{"Image":"Missing","Int":"0","Owner":null,"Trail":"0"},"6B68":{"Image":"Missing","Int":"0","Owner":null,"Trail":"0"},"6CA0":{"Image":"Missing","Int":"0","Owner":null,"Trail":"0"},"6D3B":{"Image":"Missing","Int":"0","Owner":null,"Trail":"0"},"6D8B":{"Image":"Missing","Int":"0","Owner":null,"Trail":"0"},"6E1C":{"Image":"Missing","Int":"0","Owner":null,"Trail":"0"},"6ED6":{"Image":"Missing","Int":"0","Owner":null,"Trail":"0"},"6F07":{"Image":"Missing","Int":"0","Owner":null,"Trail":"0"},"6F25":{"Image":"Missing","Int":"0","Owner":null,"Trail":"0"},"6F43":{"Image":"Missing","Int":"0","Owner":null,"Trail":"0"},"6F48":{"Image":"Missing","Int":"0","Owner":null,"Trail":"0"},"6F4A":{"Image":"Missing","Int":"0","Owner":null,"Trail":"0"},"6FE6":{"Image":"Missing","Int":"0","Owner":null,"Trail":"0"},"7033":{"Image":"Missing","Int":"0","Owner":null,"Trail":"0"},"7035":{"Image":"Missing","Int":"0","Owner":null,"Trail":"0"},"7037":{"Image":"Missing","Int":"0","Owner":null,"Trail":"0"},"7079":{"Image":"Missing","Int":"0","Owner":null,"Trail":"0"},"707B":{"Image":"Missing","Int":"0","Owner":null,"Trail":"0"},"70C1":{"Image":"Missing","Int":"0","Owner":null,"Trail":"0"},"70E3":{"Image":"Missing","Int":"0","Owner":null,"Trail":"0"},"7192":{"Image":"Missing","Int":"0","Owner":null,"Trail":"0"},"71DF":{"Image":"Missing","Int":"0","Owner":null,"Trail":"0"},"7262":{"Image":"Missing","Int":"0","Owner":null,"Trail":"0"},"7346":{"Image":"Missing","Int":"0","Owner":null,"Trail":"0"},"7361":{"Image":"Missing","Int":"0","Owner":null,"Trail":"0"},"73A2":{"Image":"Missing","Int":"0","Owner":null,"Trail":"0"},"73D3":{"Image":"Missing","Int":"0","Owner":null,"Trail":"0"},"74C6":{"Image":"Missing","Int":"0","Owner":null,"Trail":"0"},"757A":{"Image":"Missing","Int":"0","Owner":null,"Trail":"0"},"758D":{"Image":"Missing","Int":"0","Owner":null,"Trail":"0"},"758E":{"Image":"Missing","Int":"0","Owner":null,"Trail":"0"},"7595":{"Image":"Missing","Int":"0","Owner":null,"Trail":"0"},"75B8":{"Image":"Missing","Int":"0","Owner":null,"Trail":"0"},"75B9":{"Image":"Missing","Int":"0","Owner":null,"Trail":"0"},"75BA":{"Image":"Missing","Int":"0","Owner":null,"Trail":"0"},"76BF":{"Image":"Missing","Int":"0","Owner":null,"Trail":"0"},"77FA":{"Image":"Missing","Int":"0","Owner":null,"Trail":"0"},"7846":{"Image":"Missing","Int":"0","Owner":null,"Trail":"0"},"7856":{"Image":"Missing","Int":"0","Owner":null,"Trail":"0"},"7857":{"Image":"Missing","Int":"0","Owner":null,"Trail":"0"},"7859":{"Image":"Missing","Int":"0","Owner":null,"Trail":"0"},"785A":{"Image":"Missing","Int":"0","Owner":null,"Trail":"0"},"785B":{"Image":"Missing","Int":"0","Owner":null,"Trail":"0"},"785C":{"Image":"Missing","Int":"0","Owner":null,"Trail":"0"},"785F":{"Image":"Missing","Int":"0","Owner":null,"Trail":"0"},"7860":{"Image":"Missing","Int":"0","Owner":null,"Trail":"0"},"7861":{"Image":"Missing","Int":"0","Owner":null,"Trail":"0"},"7862":{"Image":"Missing","Int":"0","Owner":null,"Trail":"0"},"786A":{"Image":"Missing","Int":"0","Owner":null,"Trail":"0"},"7943":{"Image":"Missing","Int":"0","Owner":null,"Trail":"0"},"7947":{"Image":"Missing","Int":"0","Owner":null,"Trail":"0"},"7949":{"Image":"Missing","Int":"0","Owner":null,"Trail":"0"},"7953":{"Image":"Missing","Int":"0","Owner":null,"Trail":"0"},"7957":{"Image":"Missing","Int":"0","Owner":null,"Trail":"0"},"796D":{"Image":"Missing","Int":"0","Owner":null,"Trail":"0"},"7970":{"Image":"Missing","Int":"0","Owner":null,"Trail":"0"},"7AB7":{"Image":"Missing","Int":"0","Owner":null,"Trail":"0"},"7AE5":{"Image":"Missing","Int":"0","Owner":null,"Trail":"0"},"7B43":{"Image":"Missing","Int":"0","Owner":null,"Trail":"0"},"7B73":{"Image":"Missing","Int":"0","Owner":null,"Trail":"0"},"7BB3":{"Image":"Missing","Int":"0","Owner":null,"Trail":"0"},"7BB4":{"Image":"Missing","Int":"0","Owner":null,"Trail":"0"},"7BB5":{"Image":"Missing","Int":"0","Owner":null,"Trail":"0"},"7BB6":{"Image":"Missing","Int":"0","Owner":null,"Trail":"0"},"7BB7":{"Image":"Missing","Int":"0","Owner":null,"Trail":"0"},"7BB9":{"Image":"Missing","Int":"0","Owner":null,"Trail":"0"},"7C7C":{"Image":"Missing","Int":"0","Owner":null,"Trail":"0"},"7C87":{"Image":"Missing","Int":"0","Owner":null,"Trail":"0"},"7C97":{"Image":"Missing","Int":"0","Owner":null,"Trail":"0"},"7CA7":{"Country":"Unknown or unassigned co","Image":"Missing","Int":"0","Owner":null,"Trail":"0"},"7CB7":{"Image":"Missing","Int":"0","Owner":null,"Trail":"0"},"7D22":{"Image":"Missing","Int":"0","Owner":null,"Trail":"0"},"7E43":{"Image":"Missing","Int":"0","Owner":null,"Trail":"0"},"7E7E":{"Image":"Missing","Int":"0","Owner":null,"Trail":"0"},"7F5F":{"Image":"Missing","Int":"0","Owner":null,"Trail":"0"},"7F77":{"Image":"Missing","Int":"0","Owner":null,"Trail":"0"},"7F92":{"Image":"Missing","Int":"0","Owner":null,"Trail":"0"},"7F93":{"Image":"Missing","Int":"0","Owner":null,"Trail":"0"},"8027":{"Image":"Missing","Int":"0","Owner":null,"Trail":"0"},"8033":{"Image":"Missing","Int":"0","Owner":null,"Trail":"0"},"8100":{"Country":"Unknown or unassigned co","Int":"0","Owner":null,"Trail":"0"},"8129":{"Image":"Missing","Int":"0","Owner":null,"Trail":"0"},"81B6":{"Image":"Missing","Int":"0","Owner":null,"Trail":"0"},"81C8":{"Image":"Missing","Int":"0","Owner":null,"Trail":"0"},"81DF":{"Image":"Missing","Int":"0","Owner":null,"Trail":"0"},"8489":{"Image":"Missing","Int":"0","Owner":null,"Trail":"0"},"84E9":{"Image":"Missing","Int":"0","Owner":null,"Trail":"0"},"8534":{"Image":"Missing","Int":"0","Owner":null,"Trail":"0"},"8536":{"Image":"Missing","Int":"0","Owner":null,"Trail":"0"},"8549":{"Image":"Missing","Int":"0","Owner":null,"Trail":"0"},"8618":{"Image":"Missing","Int":"0","Owner":null,"Trail":"0"},"8662":{"Image":"Missing","Int":"0","Owner":null,"Trail":"0"},"8776":{"Image":"Missing","Int":"0","Owner":null,"Trail":"0"},"8800":{"Image":"Missing","Int":"0","Owner":null,"Trail":"0"},"8826":{"Image":"Missing","Int":"0","Owner":null,"Trail":"0"},"882D":{"Image":"Missing","Int":"0","Owner":null,"Trail":"0"},"89BB":{"Image":"Missing","Int":"0","Owner":null,"Trail":"0"},"8B45":{"Image":"Missing","Int":"0","Owner":null,"Trail":"0"},"8C2C":{"Image":"Missing","Int":"0","Owner":null,"Trail":"0"},"8C63":{"Image":"Missing","Int":"0","Owner":null,"Trail":"0"},"8CA9":{"Image":"Missing","Int":"0","Owner":null,"Trail":"0"},"8CD2":{"Image":"Missing","Int":"0","Owner":null,"Trail":"0"},"8CD9":{"Image":"Missing","Int":"0","Owner":null,"Trail":"0"},"8E10":{"Image":"Missing","Int":"0","Owner":null,"Trail":"0"},"8F40":{"Image":"Missing","Int":"0","Owner":null,"Trail":"0"},"8F96":{"Image":"Missing","Int":"0","Owner":null,"Trail":"0"},"9013":{"Image":"Missing","Int":"0","Owner":null,"Trail":"0"},"9027":{"Image":"Missing","Int":"0","Owner":null,"Trail":"0"},"9029":{"Image":"Missing","Int":"0","Owner":null,"Trail":"0"},"902B":{"Image":"Missing","Int":"0","Owner":null,"Trail":"0"},"902D":{"Image":"Missing","Int":"0","Owner":null,"Trail":"0"},"902F":{"Image":"Missing","Int":"0","Owner":null,"Trail":"0"},"9031":{"Image":"Missing","Int":"0","Owner":null,"Trail":"0"},"90D4":{"Image":"Missing","Int":"0","Owner":null,"Trail":"0"},"90FB":{"Image":"Missing","Int":"0","Owner":null,"Trail":"0"},"910C":{"Image":"Missing","Int":"0","Owner":null,"Trail":"0"},"91CF":{"Image":"Missing","Int":"0","Owner":null,"Trail":"0"},"91DF":{"Image":"Missing","Int":"0","Owner":null,"Trail":"0"},"9209":{"Image":"Missing","Int":"0","Owner":null,"Trail":"0"},"9251":{"Image":"Missing","Int":"0","Owner":null,"Trail":"0"},"936A":{"Image":"Missing","Int":"0","Owner":null,"Trail":"0"},"937E":{"Image":"Missing","Int":"0","Owner":null,"Trail":"0"},"9425":{"Image":"Missing","Int":"0","Owner":null,"Trail":"0"},"9441":{"Image":"Missing","Int":"0","Owner":null,"Trail":"0"},"944E":{"Image":"Missing","Int":"0","Owner":null,"Trail":"0"},"9451":{"Image":"Missing","Int":"0","Owner":null,"Trail":"0"},"94C5":{"Int":"0","Owner":null,"Trail":"0"},"950C":{"Image":"Missing","Int":"0","Owner":null,"Trail":"0"},"950E":{"Image":"Missing","Int":"0","Owner":null,"Trail":"0"},"9534":{"Image":"Missing","Int":"0","Owner":null,"Trail":"0"},"9536":{"Image":"Missing","Int":"0","Owner":null,"Trail":"0"},"963D":{"Image":"Missing","Int":"0","Owner":null,"Trail":"0"},"9652":{"Image":"Missing","Int":"0","Owner":null,"Trail":"0"},"966E":{"Image":"Missing","Int":"0","Owner":null,"Trail":"0"},"968C":{"Image":"Missing","Int":"0","Owner":null,"Trail":"0"},"9761":{"Image":"Missing","Int":"0","Owner":null,"Trail":"0"},"9781":{"Image":"Missing","Int":"0","Owner":null,"Trail":"0"},"9791":{"Image":"Missing","Int":"0","Owner":null,"Trail":"0"},"9892":{"Image":"Missing","Int":"0","Owner":null,"Trail":"0"},"9897":{"Image":"Missing","Int":"0","Owner":null,"Trail":"0"},"9900":{"Image":"Missing","Int":"0","Owner":null,"Trail":"0"},"994F":{"Image":"Missing","Int":"0","Owner":null,"Trail":"0"},"9A9B":{"Image":"Missing","Int":"0","Owner":null,"Trail":"0"},"9B96":{"Image":"Missing","Int":"0","Owner":null,"Trail":"0"},"9BA3":{"Image":"Missing","Int":"0","Owner":null,"Trail":"0"},"9BA4":{"Image":"Missing","Int":"0","Owner":null,"Trail":"0"},"9BA6":{"Image":"Missing","Int":"0","Owner":null,"Trail":"0"},"9CDA":{"Image":"Missing","Int":"0","Owner":null,"Trail":"0"},"9CE0":{"Image":"Missing","Int":"0","Owner":null,"Trail":"0"},"9F22":{"Image":"Missing","Int":"0","Owner":null,"Trail":"0"},"9F2C":{"Image":"Missing","Int":"0","Owner":null,"Trail":"0"},"9F40":{"Image":"Missing","Int":"0","Owner":null,"Trail":"0"},"9F42":{"Image":"Missing","Int":"0","Owner":null,"Trail":"0"},"A0B5":{"Image":"Missing","Int":"0","Owner":null,"Trail":"0"},"A17E":{"Image":"Missing","Int":"0","Owner":null,"Trail":"0"},"A1CF":{"Image":"Missing","Int":"0","Owner":null,"Trail":"0"},"A1DF":{"Image":"Missing","Int":"0","Owner":null,"Trail":"0"},"A281":{"Image":"Missing","Int":"0","Owner":null,"Trail":"0"},"A2C9":{"Image":"Missing","Int":"0","Owner":null,"Trail":"0"},"A2CD":{"Image":"Missing","Int":"0","Owner":null,"Trail":"0"},"A2D9":{"Image":"Missing","Int":"0","Owner":null,"Trail":"0"},"A2DD":{"Image":"Missing","Int":"0","Owner":null,"Trail":"0"},"A2E2":{"Image":"Missing","Int":"0","Owner":null,"Trail":"0"},"A2E9":{"Image":"Missing","Int":"0","Owner":null,"Trail":"0"},"A2ED":{"Image":"Missing","Int":"0","Owner":null,"Trail":"0"},"A2F1":{"Image":"Missing","Int":"0","Owner":null,"Trail":"0"},"A2F9":{"Image":"Missing","Int":"0","Owner":null,"Trail":"0"},"A307":{"Image":"Missing","Int":"0","Owner":null,"Trail":"0"},"A31C":{"Image":"Missing","Int":"0","Owner":null,"Trail":"0"},"A398":{"Image":"Missing","Int":"0","Owner":null,"Trail":"0"},"A399":{"Image":"Missing","Int":"0","Owner":null,"Trail":"0"},"A465":{"Image":"Missing","Int":"0","Owner":null,"Trail":"0"},"A469":{"Image":"Missing","Int":"0","Owner":null,"Trail":"0"},"A500":{"Image":"Missing","Int":"0","Owner":null,"Trail":"0"},"A53B":{"Image":"Missing","Int":"0","Owner":null,"Trail":"0"},"A561":{"Image":"Missing","Int":"0","Owner":null,"Trail":"0"},"A581":{"Image":"Missing","Int":"0","Owner":null,"Trail":"0"},"A663":{"Image":"Missing","Int":"0","Owner":null,"Trail":"0"},"A667":{"Image":"Missing","Int":"0","Owner":null,"Trail":"0"},"A671":{"Image":"Missing","Int":"0","Owner":null,"Trail":"0"},"A765":{"Image":"Missing","Int":"0","Owner":null,"Trail":"0"},"A793":{"Image":"Missing","Int":"0","Owner":null,"Trail":"0"},"A797":{"Image":"Missing","Int":"0","Owner":null,"Trail":"0"},"A7A7":{"Image":"Missing","Int":"0","Owner":null,"Trail":"0"},"A7B3":{"Image":"Missing","Int":"0","Owner":null,"Trail":"0"},"A7B7":{"Image":"Missing","Int":"0","Owner":null,"Trail":"0"},"A8B3":{"Image":"Missing","Int":"0","Owner":null,"Trail":"0"},"AB07":{"Image":"Missing","Int":"0","Owner":null,"Trail":"0"},"AB74":{"Image":"Missing","Int":"0","Owner":null,"Trail":"0"},"ABB7":{"Image":"Missing","Int":"0","Owner":null,"Trail":"0"},"AC40":{"Image":"Missing","Int":"0","Owner":null,"Trail":"0"},"AD69":{"Image":"Missing","Int":"0","Owner":null,"Trail":"0"},"AE42":{"Image":"Missing","Int":"0","Owner":null,"Trail":"0"},"AF22":{"Image":"Missing","Int":"0","Owner":null,"Trail":"0"},"AF42":{"Image":"Missing","Int":"0","Owner":null,"Trail":"0"},"AF44":{"Image":"Missing","Int":"0","Owner":null,"Trail":"0"},"AF4E":{"Image":"Missing","Int":"0","Owner":null,"Trail":"0"},"AFBD":{"Image":"Missing","Int":"0","Owner":null,"Trail":"0"},"AFF7":{"Image":"Missing","Int":"0","Owner":null,"Trail":"0"},"B15E":{"Image":"Missing","Int":"0","Owner":null,"Trail":"0"},"B1C7":{"Image":"Missing","Int":"0","Owner":null,"Trail":"0"},"B1C9":{"Image":"Missing","Int":"0","Owner":null,"Trail":"0"},"B1CB":{"Image":"Missing","Int":"0","Owner":null,"Trail":"0"},"B1CD":{"Image":"Missing","Int":"0","Owner":null,"Trail":"0"},"B1F8":{"Image":"Missing","Int":"0","Owner":null,"Trail":"0"},"B285":{"Image":"Missing","Int":"0","Owner":null,"Trail":"0"},"B296":{"Image":"Missing","Int":"0","Owner":null,"Trail":"0"},"B43D":{"Image":"Missing","Int":"0","Owner":null,"Trail":"0"},"B477":{"Image":"Missing","Int":"0","Owner":null,"Trail":"0"},"B485":{"Image":"Missing","Int":"0","Owner":null,"Trail":"0"},"B4E5":{"Image":"Missing","Int":"0","Owner":null,"Trail":"0"},"B50E":{"Image":"Missing","Int":"0","Owner":null,"Trail":"0"},"B607":{"Image":"Missing","Int":"0","Owner":null,"Trail":"0"},"B7ED":{"Image":"Missing","Int":"0","Owner":null,"Trail":"0"},"B8BA":{"Image":"Missing","Int":"0","Owner":null,"Trail":"0"},"B8F5":{"Image":"Missing","Int":"0","Owner":null,"Trail":"0"},"BA27":{"Image":"Missing","Int":"0","Owner":null,"Trail":"0"},"BA50":{"Image":"Missing","Int":"0","Owner":null,"Trail":"0"},"BA6D":{"Image":"Missing","Int":"0","Owner":null,"Trail":"0"},"BA8A":{"Image":"Missing","Int":"0","Owner":null,"Trail":"0"},"BB44":{"Image":"Missing","Int":"0","Owner":null,"Trail":"0"},"BB65":{"Image":"Missing","Int":"0","Owner":null,"Trail":"0"},"BB66":{"Image":"Missing","Int":"0","Owner":null,"Trail":"0"},"BB68":{"Image":"Missing","Int":"0","Owner":null,"Trail":"0"},"BB6E":{"Image":"Missing","Int":"0","Owner":null,"Trail":"0"},"BB88":{"Image":"Missing","Int":"0","Owner":null,"Trail":"0"},"BB8D":{"Image":"Missing","Int":"0","Owner":null,"Trail":"0"},"BBBC":{"Image":"Missing","Int":"0","Owner":null,"Trail":"0"},"BC35":{"Image":"Missing","Int":"0","Owner":null,"Trail":"0"},"BC4D":{"Image":"Missing","Int":"0","Owner":null,"Trail":"0"},"BC5D":{"Image":"Missing","Int":"0","Owner":null,"Trail":"0"},"BCCF":{"Image":"Missing","Int":"0","Owner":null,"Trail":"0"},"BCD9":{"Image":"Missing","Int":"0","Owner":null,"Trail":"0"},"BD08":{"Image":"Missing","Int":"0","Owner":null,"Trail":"0"},"BD17":{"Image":"Missing","Int":"0","Owner":null,"Trail":"0"},"BE0A":{"Image":"Missing","Int":"0","Owner":null,"Trail":"0"},"BE24":{"Image":"Missing","Int":"0","Owner":null,"Trail":"0"},"BE45":{"Image":"Missing","Int":"0","Owner":null,"Trail":"0"},"BED3":{"Image":"Missing","Int":"0","Owner":null,"Trail":"0"},"BEE8":{"Image":"Missing","Int":"0","Owner":null,"Trail":"0"},"BEFD":{"Image":"Missing","Int":"0","Owner":null,"Trail":"0"},"BF08":{"Image":"Missing","Int":"0","Owner":null,"Trail":"0"},"BF0E":{"Image":"Missing","Int":"0","Owner":null,"Trail":"0"},"BF26":{"Image":"Missing","Int":"0","Owner":null,"Trail":"0"},"BF42":{"Image":"Missing","Int":"0","Owner":null,"Trail":"0"},"BF44":{"Image":"Missing","Int":"0","Owner":null,"Trail":"0"},"BF77":{"Image":"Missing","Int":"0","Owner":null,"Trail":"0"},"BF97":{"Int":"0","Owner":null,"Trail":"0"},"C019":{"Image":"Missing","Int":"0","Owner":null,"Trail":"0"},"C048":{"Image":"Missing","Int":"0","Owner":null,"Trail":"0"},"C073":{"Image":"Missing","Int":"0","Owner":null,"Trail":"0"},"C078":{"Image":"Missing","Int":"0","Owner":null,"Trail":"0"},"C1CA":{"Image":"Missing","Int":"0","Owner":null,"Trail":"0"},"C30B":{"Image":"Missing","Int":"0","Owner":null,"Trail":"0"},"C59D":{"Image":"Missing","Int":"0","Owner":null,"Trail":"0"},"C5AD":{"Image":"Missing","Int":"0","Owner":null,"Trail":"0"},"C5E9":{"Image":"Missing","Int":"0","Owner":null,"Trail":"0"},"C5ED":{"Image":"Missing","Int":"0","Owner":null,"Trail":"0"},"C776":{"Image":"Missing","Int":"0","Owner":null,"Trail":"0"},"C9B4":{"Image":"Missing","Int":"0","Owner":null,"Trail":"0"},"C9B7":{"Image":"Missing","Int":"0","Owner":null,"Trail":"0"},"C9D5":{"Image":"Missing","Int":"0","Owner":null,"Trail":"0"},"C9D9":{"Image":"Missing","Int":"0","Owner":null,"Trail":"0"},"C9F5":{"Image":"Missing","Int":"0","Owner":null,"Trail":"0"},"CA19":{"Image":"Missing","Int":"0","Owner":null,"Trail":"0"},"CA98":{"Image":"Missing","Int":"0","Owner":null,"Trail":"0"},"CB88":{"Image":"Missing","Int":"0","Owner":null,"Trail":"0"},"CC2F":{"Image":"Missing","Int":"0","Owner":null,"Trail":"0"},"CD08":{"Image":"Missing","Int":"0","Owner":null,"Trail":"0"},"CE3C":{"Image":"Missing","Int":"0","Owner":null,"Trail":"0"},"CF42":{"Image":"Missing","Int":"0","Owner":null,"Trail":"0"},"CF46":{"Image":"Missing","Int":"0","Owner":null,"Trail":"0"},"CFE6":{"Image":"Missing","Int":"0","Owner":null,"Trail":"0"},"D019":{"Image":"Missing","Int":"0","Owner":null,"Trail":"0"},"D01B":{"Image":"Missing","Int":"0","Owner":null,"Trail":"0"},"D1F1":{"Image":"Missing","Int":"0","Owner":null,"Trail":"0"},"D213":{"Image":"Missing","Int":"0","Owner":null,"Trail":"0"},"D237":{"Image":"Missing","Int":"0","Owner":null,"Trail":"0"},"D25A":{"Image":"Missing","Int":"0","Owner":null,"Trail":"0"},"D2BE":{"Image":"Missing","Int":"0","Owner":null,"Trail":"0"},"D2C6":{"Image":"Missing","Int":"0","Owner":null,"Trail":"0"},"D308":{"Image":"Missing","Int":"0","Owner":null,"Trail":"0"},"D363":{"Image":"Missing","Int":"0","Owner":null,"Trail":"0"},"D42C":{"Image":"Missing","Int":"0","Owner":null,"Trail":"0"},"D4E2":{"Image":"Missing","Int":"0","Owner":null,"Trail":"0"},"D4E3":{"Int":"0","Owner":null,"Trail":"0"},"D523":{"Image":"Missing","Int":"0","Owner":null,"Trail":"0"},"D54D":{"Image":"Missing","Int":"0","Owner":null,"Trail":"0"},"D5A8":{"Image":"Missing","Int":"0","Owner":null,"Trail":"0"},"D5CA":{"Image":"Missing","Int":"0","Owner":null,"Trail":"0"},"D5CE":{"Image":"Missing","Int":"0","Owner":null,"Trail":"0"},"D612":{"Image":"Missing","Int":"0","Owner":null,"Trail":"0"},"D61E":{"Image":"Missing","Int":"0","Owner":null,"Trail":"0"},"D658":{"Image":"Missing","Int":"0","Owner":null,"Trail":"0"},"D73E":{"Image":"Missing","Int":"0","Owner":null,"Trail":"0"},"D787":{"Image":"Missing","Int":"0","Owner":null,"Trail":"0"},"D7FE":{"Image":"Missing","Int":"0","Owner":null,"Trail":"0"},"D8C4":{"Image":"Missing","Int":"0","Owner":null,"Trail":"0"},"DA13":{"Image":"Missing","Int":"0","Owner":null,"Trail":"0"},"DA45":{"Image":"Missing","Int":"0","Owner":null,"Trail":"0"},"DC62":{"Image":"Missing","Int":"0","Owner":null,"Trail":"0"},"DCE2":{"Image":"Missing","Int":"0","Owner":null,"Trail":"0"},"DDF9":{"Image":"Missing","Int":"0","Owner":null,"Trail":"0"},"DE9F":{"Image":"Missing","Int":"0","Owner":null,"Trail":"0"},"DF44":{"Image":"Missing","Int":"0","Owner":null,"Trail":"0"},"DF4A":{"Image":"Missing","Int":"0","Owner":null,"Trail":"0"},"E007":{"Image":"Missing","Int":"0","Owner":null,"Trail":"0"},"E05C":{"Image":"Missing","Int":"0","Owner":null,"Trail":"0"},"E175":{"Image":"Missing","Int":"0","Owner":null,"Trail":"0"},"E199":{"Image":"Missing","Int":"0","Owner":null,"Trail":"0"},"E19D":{"Image":"Missing","Int":"0","Owner":null,"Trail":"0"},"E288":{"Int":"0","Owner":null,"Trail":"0"},"E577":{"Image":"Missing","Int":"0","Owner":null,"Trail":"0"},"E743":{"Image":"Missing","Int":"0","Owner":null,"Trail":"0"},"EAAF":{"Image":"Missing","Int":"0","Owner":null,"Trail":"0"},"EB8C":{"Image":"Missing","Int":"0","Owner":null,"Trail":"0"},"EBBF":{"Image":"Missing","Int":"0","Owner":null,"Trail":"0"},"EC1E":{"Image":"Missing","Int":"0","Owner":null,"Trail":"0"},"EC27":{"Image":"Missing","Int":"0","Owner":null,"Trail":"0"},"EC36":{"Image":"Missing","Int":"0","Owner":null,"Trail":"0"},"EDD2":{"Image":"Missing","Int":"0","Owner":null,"Trail":"0"},"EE0A":{"Image":"Missing","Int":"0","Owner":null,"Trail":"0"},"EE0C":{"Image":"Missing","Int":"0","Owner":null,"Trail":"0"},"EE15":{"Image":"Missing","Int":"0","Owner":null,"Trail":"0"},"EEED":{"Image":"Missing","Int":"0","Owner":null,"Trail":"0"},"EEF8":{"Image":"Missing","Int":"0","Owner":null,"Trail":"0"},"EF44":{"Image":"Missing","Int":"0","Owner":null,"Trail":"0"},"EF8F":{"Image":"Missing","Int":"0","Owner":null,"Trail":"0"},"EFD5":{"Image":"Missing","Int":"0","Owner":null,"Trail":"0"},"EFE4":{"Image":"Missing","Int":"0","Owner":null,"Trail":"0"},"F00D":{"Image":"Missing","Int":"0","Owner":null,"Trail":"0"},"F00F":{"Image":"Missing","Int":"0","Owner":null,"Trail":"0"},"F073":{"Image":"Missing","Int":"0","Owner":null,"Trail":"0"},"F26F":{"Image":"Missing","Int":"0","Owner":null,"Trail":"0"},"F3F2":{"Image":"Missing","Int":"0","Owner":null,"Trail":"0"},"F485":{"Image":"Missing","Int":"0","Owner":null,"Trail":"0"},"F4AC":{"Image":"Missing","Int":"0","Owner":null,"Trail":"0"},"F4E5":{"Image":"Missing","Int":"0","Owner":null,"Trail":"0"},"F536":{"Image":"Missing","Int":"0","Owner":null,"Trail":"0"},"F55D":{"Image":"Missing","Int":"0","Owner":null,"Trail":"0"},"F606":{"Image":"Missing","Int":"0","Owner":null,"Trail":"0"},"F646":{"Image":"Missing","Int":"0","Owner":null,"Trail":"0"},"F6AF":{"Image":"Missing","Int":"0","Owner":null,"Trail":"0"},"F6D6":{"Image":"Missing","Int":"0","Owner":null,"Trail":"0"},"F6E8":{"Image":"Missing","Int":"0","Owner":null,"Trail":"0"},"F6EE":{"Image":"Missing","Int":"0","Owner":null,"Trail":"0"},"F9DF":{"Image":"Missing","Int":"0","Owner":null,"Trail":"0"},"F9F0":{"Image":"Missing","Int":"0","Owner":null,"Trail":"0"},"FAA7":{"Image":"Missing","Int":"0","Owner":null,"Trail":"0"},"FAB7":{"Image":"Missing","Int":"0","Owner":null,"Trail":"0"},"FB07":{"Image":"Missing","Int":"0","Owner":null,"Trail":"0"},"FCA7":{"Image":"Missing","Int":"0","Owner":null,"Trail":"0"},"FCA8":{"Image":"Missing","Int":"0","Owner":null,"Trail":"0"},"FEB1":{"Image":"Missing","Int":"0","Owner":null,"Trail":"0"},"FF2C":{"Image":"Missing","Int":"0","Owner":null,"Trail":"0"},"FF2E":{"Image":"Missing","Int":"0","Owner":null,"Trail":"0"},"FF38":{"Int":"0","Owner":null,"Trail":"0"},"FF40":{"Image":"Missing","Int":"0","Owner":null,"Trail":"0"},"FF42":{"Image":"Missing","Int":"0","Owner":null,"Trail":"0"},"FF44":{"Image":"Missing","Int":"0","Owner":null,"Trail":"0"},"FFE6":{"Image":"Missing","Int":"0","Owner":null,"Trail":"0"}}